{
    "raw": "{  \n  \"requirement_id\": \"R001\",  \n  \"requirement_summary\": \"Travel insurance for a trip to Europe for two adults with specific coverage needs.\",  \n  \"detailed_description\": \"Comprehensive travel insurance coverage for two adults traveling from Singapore to Europe for 3 weeks. Coverage includes medical needs due to one traveller's high blood pressure, trip cancellation protection, travel delay coverage with accommodation and meals, lost or damaged luggage protection, hiking activities, and pet accommodation costs in case of travel delays.\",  \n  \"travel_origin\": \"Singapore\",  \n  \"travel_destination\": \"Europe\",  \n  \"travel_duration\": \"3 weeks\",  \n  \"insurance_coverage_type\": [\"Comprehensive Medical Coverage\", \"Trip Cancellation\", \"Travel Delay\", \"Lost or Damaged Luggage\", \"Hiking Activities\", \"Pet Accommodation\"],  \n  \"pre_existing_conditions\": [\"High blood pressure\"],  \n  \"medical_needs\": [\"General medical cover for emergencies\", \"Hospital stays\", \"Doctor visits\"],  \n  \"activities_to_cover\": [\"Hiking\"],  \n  \"age_group\": \"41-55\",  \n  \"additional_requests\": \"Coverage for extra pet accommodation costs if return trip is delayed.\",  \n  \"keywords\": [\"travel insurance\", \"Europe\", \"trip cancellation\", \"travel delays\", \"lost luggage\", \"hiking\", \"pet accommodation\"]  \n}",
    "pydantic": null,
    "json_dict": {
        "requirement_id": "R001",
        "requirement_summary": "Travel insurance for a trip to Europe for two adults with specific coverage needs.",
        "detailed_description": "Comprehensive travel insurance coverage for two adults traveling from Singapore to Europe for 3 weeks. Coverage includes medical needs due to one traveller's high blood pressure, trip cancellation protection, travel delay coverage with accommodation and meals, lost or damaged luggage protection, hiking activities, and pet accommodation costs in case of travel delays.",
        "travel_origin": "Singapore",
        "travel_destination": "Europe",
        "travel_duration": "3 weeks",
        "insurance_coverage_type": [
            "Comprehensive Medical Coverage",
            "Trip Cancellation",
            "Travel Delay",
            "Lost or Damaged Luggage",
            "Hiking Activities",
            "Pet Accommodation"
        ],
        "pre_existing_conditions": [
            "High blood pressure"
        ],
        "medical_needs": [
            "General medical cover for emergencies",
            "Hospital stays",
            "Doctor visits"
        ],
        "activities_to_cover": [
            "Hiking"
        ],
        "age_group": "41-55",
        "additional_requests": "Coverage for extra pet accommodation costs if return trip is delayed.",
        "keywords": [
            "travel insurance",
            "Europe",
            "trip cancellation",
            "travel delays",
            "lost luggage",
            "hiking",
            "pet accommodation"
        ]
    },
    "tasks_output": [
        {
            "description": "Analyze the travel insurance call transcript below and extract key customer requirements.\nStep 1: Read the transcript carefully and extract all relevant details. For each field in the schema, provide a brief annotation or reference to the specific portion(s) of the transcript where the detail was found.\nStep 2: Review your annotations to verify that every extracted detail directly matches the transcript. Resolve any discrepancies or conflicts in the data.\nStep 3: Produce a final, validated JSON object that adheres exactly to the TravelInsuranceRequirement schema\n\nIf a field is not mentioned in the transcript, use null.\n\nTranscript:\nCustomer Service Agent: Thank you for calling ISS Insurance Ltd Singapore. My name is Priya, how may I assist you today?\nCustomer: Yes, finally. I need travel insurance. We're planning a trip to Europe. We're based in Singapore, obviously.\nCustomer Service Agent: Certainly, I can help gather your requirements for a quote. Could you let me know the duration of your trip and how many people will be travelling?\nCustomer: It's for 3 weeks. There will be 2 of us traveling. Look, I've been a loyal ISS customer for ages, so I expect the best coverage, understand?\nCustomer Service Agent: Thank you for that information, noted. And may I know the approximate age group of the travellers?\nCustomer: We're mostly around 41-55 years old. Don't try selling us some basic plan meant for youngsters.\nCustomer Service Agent: Understood. Are there any specific activities you plan to participate in during your trip to Europe?\nCustomer: We plan to do some Hiking. Nothing extreme, but if something happens, ISS better cover it. I don't want any excuses about 'high-risk activities' not being covered if we twist an ankle or something.\nCustomer Service Agent: Okay, noted hiking as an activity. For planning purposes, are there any health considerations or pre-existing medical conditions we should be aware of for either traveller? Or any specific medical equipment you might be bringing?\nCustomer: Well, one traveler has high blood pressure, but it's managed. Don't tell me that's going to be an issue for coverage, that would be ridiculous. It better not exclude anything related to that. No special equipment needed.\nCustomer Service Agent: Thank you for letting me know about the high blood pressure. So, general medical cover for emergencies during the trip is important?\nCustomer: Of course it is! What kind of question is that? Hospital stays, doctors... the works. And what if we have to cancel the whole thing before we even leave? Things happen. Illness, family emergencies... I expect full reimbursement for our flights and hotels if we can't go. Don't try to nickel-and-dime me on covered reasons.\nCustomer Service Agent: Okay, so trip cancellation protection is a requirement. What about potential issues during the travel itself?\nCustomer: Like what? Flight delays? Yes, absolutely. These airlines are completely unreliable nowadays. If we get stuck somewhere because of a major delay, ISS needs to pay for decent hotels and meals until we can get going again. And don't quote me some silly minimum delay like 12 hours before coverage kicks in, it needs to be reasonable.\nCustomer Service Agent: Noted, cover for significant travel delays causing additional expenses.\nCustomer: And luggage! Don't get me started. They always seem to lose or damage bags between connections. I need proper reimbursement if my things go missing or turn up broken. Not some token amount that barely covers a toothbrush. It needs to cover the actual value.\nCustomer Service Agent: Alright, coverage for lost, damaged, or delayed baggage. Are there any other specific concerns or situations you need cover for?\nCustomer: Yes, actually. This is very important. We have a cat here in Singapore. If our flight back is delayed significantly – say, by a day or two – we need coverage for the extra costs of keeping her in the pet hotel or kennel. That absolutely must be included, no arguments. It's a direct consequence of a travel delay.\nCustomer Service Agent: Okay, I've noted that specific requirement: cover for additional pet accommodation costs, like a pet hotel for your cat, if your return to Singapore is delayed due to a covered reason.\nCustomer: Good. Make sure it's properly covered. What about the budget? You need to know that?\nCustomer Service Agent: It helps us find suitable options. Do you have a specific budget range in mind for the premium? Perhaps $100-$200, $200-$300, around $400, or is it flexible?\nCustomer: My budget is flexible, but that doesn't mean you can overcharge me. I expect top-tier service and coverage for a fair price, especially given my loyalty. Just get this done right.\nCustomer Service Agent: Alright. So, just to confirm the requirements I've gathered for your quote: Travel insurance for 2 adults, age group 41-55, travelling from Singapore to Europe for 3 weeks. Key requirements include: Comprehensive Medical Coverage, accounting for one traveller with high blood pressure; Trip Cancellation protection for major reasons like illness or family emergency; cover for significant Travel Delays including accommodation and meals; substantial Lost or Damaged Luggage protection; specific coverage for Hiking activities; and a specific provision for additional pet accommodation costs in Singapore if your return trip is significantly delayed. Is that correct?\nCustomer: Yes, that sounds about right. Make sure that pet hotel part is definitely in there, no ambiguity. And I expect a competitive quote promptly. If there are any issues with the quote or the coverage detail isn't clear, I'll need to speak to a manager directly.\nCustomer Service Agent: Thank you for confirming. I have noted all your requirements clearly. We will use this information to identify suitable plan options and prepare a quotation for you. Someone will be in touch regarding the next steps.\nCustomer: Fine. Make it quick. Don't waste my time.\n",
            "name": null,
            "expected_output": "A JSON object that matches the TravelInsuranceRequirement model.",
            "summary": "Analyze the travel insurance call transcript below and extract key...",
            "raw": "{  \n  \"requirement_id\": \"R001\",  \n  \"requirement_summary\": \"Travel insurance for a trip to Europe for two adults with specific coverage needs.\",  \n  \"detailed_description\": \"Comprehensive travel insurance coverage for two adults traveling from Singapore to Europe for 3 weeks. Coverage includes medical needs due to one traveller's high blood pressure, trip cancellation protection, travel delay coverage with accommodation and meals, lost or damaged luggage protection, hiking activities, and pet accommodation costs in case of travel delays.\",  \n  \"travel_origin\": \"Singapore\",  \n  \"travel_destination\": \"Europe\",  \n  \"travel_duration\": \"3 weeks\",  \n  \"insurance_coverage_type\": [\"Comprehensive Medical Coverage\", \"Trip Cancellation\", \"Travel Delay\", \"Lost or Damaged Luggage\", \"Hiking Activities\", \"Pet Accommodation\"],  \n  \"pre_existing_conditions\": [\"High blood pressure\"],  \n  \"medical_needs\": [\"General medical cover for emergencies\", \"Hospital stays\", \"Doctor visits\"],  \n  \"activities_to_cover\": [\"Hiking\"],  \n  \"age_group\": \"41-55\",  \n  \"additional_requests\": \"Coverage for extra pet accommodation costs if return trip is delayed.\",  \n  \"keywords\": [\"travel insurance\", \"Europe\", \"trip cancellation\", \"travel delays\", \"lost luggage\", \"hiking\", \"pet accommodation\"]  \n}",
            "pydantic": null,
            "json_dict": {
                "requirement_id": "R001",
                "requirement_summary": "Travel insurance for a trip to Europe for two adults with specific coverage needs.",
                "detailed_description": "Comprehensive travel insurance coverage for two adults traveling from Singapore to Europe for 3 weeks. Coverage includes medical needs due to one traveller's high blood pressure, trip cancellation protection, travel delay coverage with accommodation and meals, lost or damaged luggage protection, hiking activities, and pet accommodation costs in case of travel delays.",
                "travel_origin": "Singapore",
                "travel_destination": "Europe",
                "travel_duration": "3 weeks",
                "insurance_coverage_type": [
                    "Comprehensive Medical Coverage",
                    "Trip Cancellation",
                    "Travel Delay",
                    "Lost or Damaged Luggage",
                    "Hiking Activities",
                    "Pet Accommodation"
                ],
                "pre_existing_conditions": [
                    "High blood pressure"
                ],
                "medical_needs": [
                    "General medical cover for emergencies",
                    "Hospital stays",
                    "Doctor visits"
                ],
                "activities_to_cover": [
                    "Hiking"
                ],
                "age_group": "41-55",
                "additional_requests": "Coverage for extra pet accommodation costs if return trip is delayed.",
                "keywords": [
                    "travel insurance",
                    "Europe",
                    "trip cancellation",
                    "travel delays",
                    "lost luggage",
                    "hiking",
                    "pet accommodation"
                ]
            },
            "agent": "Call Transcript Analyst",
            "output_format": "json"
        }
    ],
    "token_usage": {
        "total_tokens": 65158,
        "prompt_tokens": 54917,
        "cached_prompt_tokens": 0,
        "completion_tokens": 10241,
        "successful_requests": 35
    }
}