{
    "raw": "{\n  \"requirement_id\": \"001\",\n  \"requirement_summary\": \"Travel insurance requirements for a trip to Japan for two adults with specific coverage needs.\",\n  \"detailed_description\": \"The customer is seeking comprehensive travel insurance for a trip from Singapore to Japan for 10 days. Coverage should include medical coverage for pre-existing conditions, cancellation, travel delays, additional pet accommodation, and lost or damaged luggage.\",\n  \"travel_origin\": \"Singapore\",\n  \"travel_destination\": \"Japan\",\n  \"travel_duration\": \"10 days\",\n  \"insurance_coverage_type\": [\n    \"comprehensive medical\",\n    \"trip cancellation\",\n    \"travel delay\",\n    \"pet accommodation\",\n    \"lost or damaged luggage\"\n  ],\n  \"pre_existing_conditions\": [\n    \"high blood pressure\"\n  ],\n  \"medical_needs\": [\n    \"medical coverage\"\n  ],\n  \"activities_to_cover\": [\n    \"hiking\"\n  ],\n  \"age_group\": \"41-55\",\n  \"additional_requests\": \"Budget of $200-$300 for insurance.\",\n  \"keywords\": [\n    \"travel insurance\",\n    \"Japan\",\n    \"medical coverage\",\n    \"trip cancellation\",\n    \"travel delays\",\n    \"pet accommodation\",\n    \"lost luggage\"\n  ]\n}",
    "pydantic": null,
    "json_dict": {
        "requirement_id": "001",
        "requirement_summary": "Travel insurance requirements for a trip to Japan for two adults with specific coverage needs.",
        "detailed_description": "The customer is seeking comprehensive travel insurance for a trip from Singapore to Japan for 10 days. Coverage should include medical coverage for pre-existing conditions, cancellation, travel delays, additional pet accommodation, and lost or damaged luggage.",
        "travel_origin": "Singapore",
        "travel_destination": "Japan",
        "travel_duration": "10 days",
        "insurance_coverage_type": [
            "comprehensive medical",
            "trip cancellation",
            "travel delay",
            "pet accommodation",
            "lost or damaged luggage"
        ],
        "pre_existing_conditions": [
            "high blood pressure"
        ],
        "medical_needs": [
            "medical coverage"
        ],
        "activities_to_cover": [
            "hiking"
        ],
        "age_group": "41-55",
        "additional_requests": "Budget of $200-$300 for insurance.",
        "keywords": [
            "travel insurance",
            "Japan",
            "medical coverage",
            "trip cancellation",
            "travel delays",
            "pet accommodation",
            "lost luggage"
        ]
    },
    "tasks_output": [
        {
            "description": "Analyze the travel insurance call transcript below and extract key customer requirements.\nStep 1: Read the transcript carefully and extract all relevant details. For each field in the schema, provide a brief annotation or reference to the specific portion(s) of the transcript where the detail was found.\nStep 2: Review your annotations to verify that every extracted detail directly matches the transcript. Resolve any discrepancies or conflicts in the data.\nStep 3: Produce a final, validated JSON object that adheres exactly to the TravelInsuranceRequirement schema\n\nIf a field is not mentioned in the transcript, use null.\n\nTranscript:\nCustomer Service Agent: Thank you for calling ISS Insurance Ltd Singapore. My name is Priya, how may I help you today?\nCustomer: Oh, hello? Yes, um, hi. I need... I need to ask about travel insurance. It’s all just… so much. I’m planning a trip and honestly, I’m feeling completely overwhelmed by everything. I don't even know where to start.\nCustomer Service Agent: I understand planning can be stressful. Take a deep breath, I'm here to help gather the details. Could you tell me where you'll be traveling to?\nCustomer: Right, yes. Sorry. We're planning a trip to Japan. It just seems so complicated, all the forms and what-ifs...\nCustomer Service Agent: Japan is a popular destination. And how long will you be away for?\nCustomer: Uh, 10 days. We'll be traveling from Singapore, obviously. It’s just… 10 days feels like a long time for something to go wrong.\nCustomer Service Agent: Okay, noted. Traveling from Singapore to Japan for 10 days. And how many people will be traveling on this policy?\nCustomer: There will be 2 of us traveling. Just my husband and myself. We're both... well, let's just say we're in the 41-55 age group.\nCustomer Service Agent: Alright, two travelers, 41 to 55 years old. Thank you. Are there any particular health concerns or pre-existing medical conditions I should note for the travelers?\nCustomer: Yes! That’s one thing… my husband has high blood pressure. It’s managed, but… what if something happens over there? The hospitals, the costs… I just panic thinking about needing medical coverage, you know? It needs to be covered properly. I can't handle that kind of stress.\nCustomer Service Agent: Okay, I've noted the requirement for medical coverage, and specifically noted the mention of high blood pressure. And what sort of activities are you planning during your trip to Japan? Anything adventurous?\nCustomer: Oh, um, we wanted to do some hiking. Nothing crazy, just some nice trails. But... what if one of us falls? Twists an ankle or something worse? Is that covered under normal medical things, or is it separate? It’s just another worry… Needing help for injuries during activities like that is important.\nCustomer Service Agent: Understood, potential coverage for hiking activities. And are you thinking about situations that might prevent you from going on the trip altogether?\nCustomer: Oh god, yes. Absolutely. What if one of us gets sick right before we leave? Or something happens with his high blood pressure... or even a family emergency back here? We've paid so much for flights and hotels already... losing all that money... it makes me sick to my stomach. We definitely need cover if we have to cancel the trip for reasons like illness.\nCustomer Service Agent: Okay, so cover for trip cancellation is a requirement. Now, thinking about the journey itself, do you have concerns about potential disruptions to your travel schedule?\nCustomer: Definitely! We had a terrible experience last year, stuck at an airport for ages because of a delay. It was a nightmare! What if our flight gets massively delayed? Where would we stay? Who pays for the extra hotel nights or food? It’s just… unthinkable. We need something for travel delays, proper coverage for those extra expenses.\nCustomer: And… related to that… this is honestly keeping me up at night. My cat, Mittens. She’ll be staying at a pet hotel here in Singapore while we’re away. If *our* flight back is delayed, significantly delayed I mean, the kennel costs will just pile up! It's already expensive. I absolutely need to know if insurance can cover those additional pet accommodation costs if our return to Singapore is delayed. That’s crucial.\nCustomer Service Agent: Understood, I've noted the specific requirement regarding potential coverage for additional pet accommodation fees due to a delayed return trip. Are there any other aspects of the trip you're concerned about, perhaps regarding your belongings?\nCustomer: Oh! Yes, luggage! What if the airline loses our bags? Or they arrive damaged? We’ll have our hiking boots and some specific gear… replacing it would be a disaster and so stressful. So, yes, coverage for lost or damaged luggage is definitely needed. It feels like everything could go wrong!\nCustomer Service Agent: Okay, coverage for lost or damaged luggage noted. One last question, do you have a budget range in mind for the travel insurance policy itself?\nCustomer: Look, the trip is already costing a fortune... We were hoping to spend maybe somewhere around $200-$300 for the insurance? Is that realistic? I don’t know, I just need peace of mind without breaking the bank.\nCustomer Service Agent: Okay, thank you for sharing all that information. Just to confirm I've captured everything correctly: you're looking for travel insurance for two adults, aged 41-55, traveling from Singapore to Japan for 10 days. The key requirements you've mentioned are: comprehensive medical coverage, noting the pre-existing high blood pressure; coverage for trip cancellation due to unforeseen events like illness; cover for significant travel delays including accommodation and meals; specific cover for additional pet accommodation costs if your return flight is delayed; cover for potential injuries during hiking activities; and coverage for lost or damaged luggage. You also mentioned a budget preference of around $200-$300. Does that sound accurate?\nCustomer: Yes... yes, I think that's everything. Hearing it listed out… it does help a bit. It's just been so stressful trying to think of it all.\nCustomer Service Agent: I understand completely. Thank you for your patience in going through this. I have noted all these requirements clearly. We will use this information to identify suitable options based on what you've told me. Thank you for calling ISS Insurance.\nCustomer: Okay... thank you. Thank you for your help, Priya. Bye.\n",
            "name": null,
            "expected_output": "A JSON object that matches the TravelInsuranceRequirement model.",
            "summary": "Analyze the travel insurance call transcript below and extract key...",
            "raw": "{\n  \"requirement_id\": \"001\",\n  \"requirement_summary\": \"Travel insurance requirements for a trip to Japan for two adults with specific coverage needs.\",\n  \"detailed_description\": \"The customer is seeking comprehensive travel insurance for a trip from Singapore to Japan for 10 days. Coverage should include medical coverage for pre-existing conditions, cancellation, travel delays, additional pet accommodation, and lost or damaged luggage.\",\n  \"travel_origin\": \"Singapore\",\n  \"travel_destination\": \"Japan\",\n  \"travel_duration\": \"10 days\",\n  \"insurance_coverage_type\": [\n    \"comprehensive medical\",\n    \"trip cancellation\",\n    \"travel delay\",\n    \"pet accommodation\",\n    \"lost or damaged luggage\"\n  ],\n  \"pre_existing_conditions\": [\n    \"high blood pressure\"\n  ],\n  \"medical_needs\": [\n    \"medical coverage\"\n  ],\n  \"activities_to_cover\": [\n    \"hiking\"\n  ],\n  \"age_group\": \"41-55\",\n  \"additional_requests\": \"Budget of $200-$300 for insurance.\",\n  \"keywords\": [\n    \"travel insurance\",\n    \"Japan\",\n    \"medical coverage\",\n    \"trip cancellation\",\n    \"travel delays\",\n    \"pet accommodation\",\n    \"lost luggage\"\n  ]\n}",
            "pydantic": null,
            "json_dict": {
                "requirement_id": "001",
                "requirement_summary": "Travel insurance requirements for a trip to Japan for two adults with specific coverage needs.",
                "detailed_description": "The customer is seeking comprehensive travel insurance for a trip from Singapore to Japan for 10 days. Coverage should include medical coverage for pre-existing conditions, cancellation, travel delays, additional pet accommodation, and lost or damaged luggage.",
                "travel_origin": "Singapore",
                "travel_destination": "Japan",
                "travel_duration": "10 days",
                "insurance_coverage_type": [
                    "comprehensive medical",
                    "trip cancellation",
                    "travel delay",
                    "pet accommodation",
                    "lost or damaged luggage"
                ],
                "pre_existing_conditions": [
                    "high blood pressure"
                ],
                "medical_needs": [
                    "medical coverage"
                ],
                "activities_to_cover": [
                    "hiking"
                ],
                "age_group": "41-55",
                "additional_requests": "Budget of $200-$300 for insurance.",
                "keywords": [
                    "travel insurance",
                    "Japan",
                    "medical coverage",
                    "trip cancellation",
                    "travel delays",
                    "pet accommodation",
                    "lost luggage"
                ]
            },
            "agent": "Call Transcript Analyst",
            "output_format": "json"
        }
    ],
    "token_usage": {
        "total_tokens": 77855,
        "prompt_tokens": 65657,
        "cached_prompt_tokens": 0,
        "completion_tokens": 12198,
        "successful_requests": 42
    }
}