{
    "raw": "{\n  \"requirement_id\": \"1\",\n  \"requirement_summary\": \"Travel insurance required for trip to Australia with specific coverage needs.\",\n  \"detailed_description\": \"The customer requires comprehensive travel insurance coverage for a 10-day trip to Australia, including details on medical coverage, trip cancellation, coverage for golf activities, and protection for luggage losses or damages.\",\n  \"travel_origin\": \"Singapore\",\n  \"travel_destination\": \"Australia\",\n  \"travel_duration\": \"10 days\",\n  \"insurance_coverage_type\": [\n    \"Medical Coverage\",\n    \"Trip Cancellation\",\n    \"Travel Delays\",\n    \"Lost/Damaged Luggage\",\n    \"Golf Equipment Coverage\"\n  ],\n  \"pre_existing_conditions\": null,\n  \"medical_needs\": [\n    \"Emergency medical treatment\",\n    \"Hospital stays\",\n    \"Prescriptions\",\n    \"Doctor visits\"\n  ],\n  \"activities_to_cover\": [\n    \"Golf\"\n  ],\n  \"age_group\": \"41-55\",\n  \"additional_requests\": \"Hole-in-One achievement benefit, details on reimbursement for unused green fees, and specifics on coverage for delayed flights.\",\n  \"keywords\": [\n    \"trip cancellation\",\n    \"medical coverage\",\n    \"golf equipment\",\n    \"travel delays\",\n    \"luggage coverage\"\n  ]\n}",
    "pydantic": null,
    "json_dict": {
        "requirement_id": "1",
        "requirement_summary": "Travel insurance required for trip to Australia with specific coverage needs.",
        "detailed_description": "The customer requires comprehensive travel insurance coverage for a 10-day trip to Australia, including details on medical coverage, trip cancellation, coverage for golf activities, and protection for luggage losses or damages.",
        "travel_origin": "Singapore",
        "travel_destination": "Australia",
        "travel_duration": "10 days",
        "insurance_coverage_type": [
            "Medical Coverage",
            "Trip Cancellation",
            "Travel Delays",
            "Lost/Damaged Luggage",
            "Golf Equipment Coverage"
        ],
        "pre_existing_conditions": null,
        "medical_needs": [
            "Emergency medical treatment",
            "Hospital stays",
            "Prescriptions",
            "Doctor visits"
        ],
        "activities_to_cover": [
            "Golf"
        ],
        "age_group": "41-55",
        "additional_requests": "Hole-in-One achievement benefit, details on reimbursement for unused green fees, and specifics on coverage for delayed flights.",
        "keywords": [
            "trip cancellation",
            "medical coverage",
            "golf equipment",
            "travel delays",
            "luggage coverage"
        ]
    },
    "tasks_output": [
        {
            "description": "Analyze the travel insurance call transcript below and extract key customer requirements.\nStep 1: Read the transcript carefully and extract all relevant details. For each field in the schema, provide a brief annotation or reference to the specific portion(s) of the transcript where the detail was found.\nStep 2: Review your annotations to verify that every extracted detail directly matches the transcript. Resolve any discrepancies or conflicts in the data.\nStep 3: Produce a final, validated JSON object that adheres exactly to the TravelInsuranceRequirement schema\n\nIf a field is not mentioned in the transcript, use null.\n\nTranscript:\nCustomer Service Agent: Thank you for calling ISS Insurance Ltd. My name is Sarah. How may I help you today?\nCustomer: Yes, hello. I need to inquire about travel insurance. Frankly, I'm always a bit wary of these policies, seems like companies always find ways not to pay out. But fine, let's see what you offer.\nCustomer Service Agent: I understand your concern, sir. I can certainly help gather the details of the coverage you're looking for. To start, could you let me know where you'll be traveling from?\nCustomer: We're based in Singapore. The trip starts here.\nCustomer Service Agent: Thank you. And where will you be traveling to?\nCustomer: We're planning a trip to Australia. If everything goes according to plan, that is.\nCustomer Service Agent: Understood. Australia. And how long will you be away for?\nCustomer: It will be a 10 days trip.\nCustomer Service Agent: Alright, 10 days to Australia. And how many people will be traveling?\nCustomer: There will be 2 of us traveling. Just my wife and myself.\nCustomer Service Agent: Two travelers. Could you share the general age group for both travelers?\nCustomer: We're mostly around 41-55 years old. Why, does that affect the premium drastically?\nCustomer Service Agent: It's one factor we consider when preparing a quote, just helps us understand the profile. Thank you. Now, regarding the trip itself, are there any specific health considerations or medical equipment needs I should note down?\nCustomer: No, no special medical equipment needed. But what happens if one of us suddenly needs a doctor or hospital over there? How extensive is this 'medical coverage' you claim to provide? Does it actually cover hospital stays and medication, or is it just basic first aid?\nCustomer Service Agent: Okay, so noting down the need for information on Medical Coverage, specifically covering emergency treatment, hospital stays, prescriptions, and doctor visits. Are there any pre-existing medical conditions I should be aware of for either traveler?\nCustomer: No, no pre-existing conditions. But I've heard stories... you wouldn't just use some minor thing later as an excuse to deny a claim, would you?\nCustomer Service Agent: Duly noted, sir. No declared pre-existing conditions, but you have questions about how that relates to claims. What about the purpose of your trip? Are there any specific activities planned?\nCustomer: Yes, the main reason is golf. And this is where I expect the fine print to bite. I need proper coverage for my golf equipment â€“ what if the airline loses it or damages it? That stuff is expensive. And what if I get sick halfway through and can't use the green fees I've already paid? Will I get that money back? I doubt it. Also, those golf buggies... what if I accidentally damage one? Are you going to cover that or leave me with a huge bill?\nCustomer Service Agent: Okay, so specific coverage related to golf is a key requirement. Let me note that down: protection for golf equipment against loss or damage, reimbursement for unused pre-paid green fees due to unforeseen circumstances like illness, and coverage for accidental damage to a rented golf buggy. Is that correct?\nCustomer: Yes, exactly. And I saw something online somewhere, some companies offer a little bonus if you hit a hole-in-one during the trip. Is that something ISS does, or is it just a marketing trick? I want that noted too.\nCustomer Service Agent: Understood. Noting a specific requirement for a Hole-in-One achievement benefit during the trip. Thank you. Apart from golf, any other specific activities like diving or hiking?\nCustomer: No, no special activities planned other than golf.\nCustomer Service Agent: Alright. Thinking about potential travel hiccups, what are your concerns regarding flight issues?\nCustomer: Well, you know how flights are these days. Delays are common. If we get stuck for hours, let's say more than 6 or 8 hours, does the insurance actually help with unexpected hotel or meal costs? Or is that another area with loopholes?\nCustomer Service Agent: Okay, so you require details on Travel Delays coverage, including what's provided for accommodation and meals during significant delays.\nCustomer Service Agent: And regarding luggage, besides the golf clubs, what about general checked baggage? If bags get lost or damaged by the airline, what kind of coverage is there? I need to understand the actual limits and process, not just vague promises.\nCustomer Service Agent: Noting down the need for Lost/Damaged Luggage coverage for general baggage as well, clarifying reimbursement details.\nCustomer Service Agent: What about the possibility of having to cancel the trip entirely before you even leave Singapore? Say, due to a sudden serious illness or an emergency? Is that something you need cover for?\nCustomer: Yes, absolutely. What if one of us breaks a leg a week before we fly? Or a family emergency? You have to cover trip cancellation for genuine reasons like illness or injury, right? Not just if *we* change our minds, obviously, but for real problems.\nCustomer Service Agent: Understood. So, Trip Cancellation coverage for reasons like unforeseen illness or injury is a requirement.\nCustomer Service Agent: Thank you, sir. Just to confirm, I've noted down the following requirements for your travel insurance inquiry for two adults, aged 41-55, traveling from Singapore to Australia for 10 days:\nCustomer: Yes, that covers the main points I'm concerned about. I'll need to see the actual policy wording and probably speak to someone higher up before I commit to anything, mind you. I need to be sure these things are actually covered properly. What's the typical budget for this kind of thing?\nCustomer Service Agent: I understand. My role today is just to capture these requirements accurately. I've noted your request for detailed policy wording and potentially speaking with a senior representative later. I don't provide quotes directly, but these details will allow the relevant team to prepare the information for you. Thank you for outlining your needs clearly.\nCustomer: Alright then. Make sure all those points are addressed. Thank you.\nCustomer Service Agent: Will do. Thank you for calling ISS Insurance Ltd. Have a good day.\nCustomer: You too. Goodbye.\n",
            "name": null,
            "expected_output": "A JSON object that matches the TravelInsuranceRequirement model.",
            "summary": "Analyze the travel insurance call transcript below and extract key...",
            "raw": "{\n  \"requirement_id\": \"1\",\n  \"requirement_summary\": \"Travel insurance required for trip to Australia with specific coverage needs.\",\n  \"detailed_description\": \"The customer requires comprehensive travel insurance coverage for a 10-day trip to Australia, including details on medical coverage, trip cancellation, coverage for golf activities, and protection for luggage losses or damages.\",\n  \"travel_origin\": \"Singapore\",\n  \"travel_destination\": \"Australia\",\n  \"travel_duration\": \"10 days\",\n  \"insurance_coverage_type\": [\n    \"Medical Coverage\",\n    \"Trip Cancellation\",\n    \"Travel Delays\",\n    \"Lost/Damaged Luggage\",\n    \"Golf Equipment Coverage\"\n  ],\n  \"pre_existing_conditions\": null,\n  \"medical_needs\": [\n    \"Emergency medical treatment\",\n    \"Hospital stays\",\n    \"Prescriptions\",\n    \"Doctor visits\"\n  ],\n  \"activities_to_cover\": [\n    \"Golf\"\n  ],\n  \"age_group\": \"41-55\",\n  \"additional_requests\": \"Hole-in-One achievement benefit, details on reimbursement for unused green fees, and specifics on coverage for delayed flights.\",\n  \"keywords\": [\n    \"trip cancellation\",\n    \"medical coverage\",\n    \"golf equipment\",\n    \"travel delays\",\n    \"luggage coverage\"\n  ]\n}",
            "pydantic": null,
            "json_dict": {
                "requirement_id": "1",
                "requirement_summary": "Travel insurance required for trip to Australia with specific coverage needs.",
                "detailed_description": "The customer requires comprehensive travel insurance coverage for a 10-day trip to Australia, including details on medical coverage, trip cancellation, coverage for golf activities, and protection for luggage losses or damages.",
                "travel_origin": "Singapore",
                "travel_destination": "Australia",
                "travel_duration": "10 days",
                "insurance_coverage_type": [
                    "Medical Coverage",
                    "Trip Cancellation",
                    "Travel Delays",
                    "Lost/Damaged Luggage",
                    "Golf Equipment Coverage"
                ],
                "pre_existing_conditions": null,
                "medical_needs": [
                    "Emergency medical treatment",
                    "Hospital stays",
                    "Prescriptions",
                    "Doctor visits"
                ],
                "activities_to_cover": [
                    "Golf"
                ],
                "age_group": "41-55",
                "additional_requests": "Hole-in-One achievement benefit, details on reimbursement for unused green fees, and specifics on coverage for delayed flights.",
                "keywords": [
                    "trip cancellation",
                    "medical coverage",
                    "golf equipment",
                    "travel delays",
                    "luggage coverage"
                ]
            },
            "agent": "Call Transcript Analyst",
            "output_format": "json"
        }
    ],
    "token_usage": {
        "total_tokens": 9018,
        "prompt_tokens": 7709,
        "cached_prompt_tokens": 0,
        "completion_tokens": 1309,
        "successful_requests": 5
    }
}