{
    "raw": "{\n  \"requirement_id\": \"1\",\n  \"requirement_summary\": \"Travel insurance requirement for a trip to Japan.\",\n  \"detailed_description\": \"The customer requires travel insurance for two adults traveling from Singapore to Japan for two weeks. They need coverage for medical emergencies, including a condition of high blood pressure, trip cancellation due to unexpected illness, coverage for travel delays, protection for lost or damaged luggage, and specific coverage for hiking activities. Additionally, they require information on double payout for accidental death occurring on public transport. The budget for the insurance premium is around $200-$300.\",\n  \"travel_origin\": \"Singapore\",\n  \"travel_destination\": \"Japan\",\n  \"travel_duration\": \"2 weeks\",\n  \"insurance_coverage_type\": [\n    \"Medical Coverage\",\n    \"Trip Cancellation\",\n    \"Travel Delays\",\n    \"Lost or Damaged Luggage\",\n    \"Sports and Adventure Activities\"\n  ],\n  \"pre_existing_conditions\": [\n    \"High blood pressure\"\n  ],\n  \"medical_needs\": [\n    \"Emergency medical treatment\"\n  ],\n  \"activities_to_cover\": [\n    \"Hiking\"\n  ],\n  \"age_group\": \"41-55\",\n  \"additional_requests\": \"Double payout for accidental death occurring while using public transport.\",\n  \"keywords\": [\n    \"travel insurance\",\n    \"Japan\",\n    \"medical coverage\",\n    \"trip cancellation\",\n    \"travel delays\",\n    \"lost luggage\",\n    \"hiking\",\n    \"accidental death\",\n    \"public transport\"\n  ]\n}",
    "pydantic": null,
    "json_dict": {
        "requirement_id": "1",
        "requirement_summary": "Travel insurance requirement for a trip to Japan.",
        "detailed_description": "The customer requires travel insurance for two adults traveling from Singapore to Japan for two weeks. They need coverage for medical emergencies, including a condition of high blood pressure, trip cancellation due to unexpected illness, coverage for travel delays, protection for lost or damaged luggage, and specific coverage for hiking activities. Additionally, they require information on double payout for accidental death occurring on public transport. The budget for the insurance premium is around $200-$300.",
        "travel_origin": "Singapore",
        "travel_destination": "Japan",
        "travel_duration": "2 weeks",
        "insurance_coverage_type": [
            "Medical Coverage",
            "Trip Cancellation",
            "Travel Delays",
            "Lost or Damaged Luggage",
            "Sports and Adventure Activities"
        ],
        "pre_existing_conditions": [
            "High blood pressure"
        ],
        "medical_needs": [
            "Emergency medical treatment"
        ],
        "activities_to_cover": [
            "Hiking"
        ],
        "age_group": "41-55",
        "additional_requests": "Double payout for accidental death occurring while using public transport.",
        "keywords": [
            "travel insurance",
            "Japan",
            "medical coverage",
            "trip cancellation",
            "travel delays",
            "lost luggage",
            "hiking",
            "accidental death",
            "public transport"
        ]
    },
    "tasks_output": [
        {
            "description": "Analyze the travel insurance call transcript below and extract key customer requirements.\nStep 1: Read the transcript carefully and extract all relevant details. For each field in the schema, provide a brief annotation or reference to the specific portion(s) of the transcript where the detail was found.\nStep 2: Review your annotations to verify that every extracted detail directly matches the transcript. Resolve any discrepancies or conflicts in the data.\nStep 3: Produce a final, validated JSON object that adheres exactly to the TravelInsuranceRequirement schema\n\nIf a field is not mentioned in the transcript, use null.\n\nTranscript:\nCustomer Service Agent: Thank you for calling ISS Insurance Ltd Singapore. My name is Kevin, how can I help you today?\nCustomer: Oh, hello? Kevin? Yes, hi. I… I need some help. Travel insurance. It’s all just… so much. My head is spinning trying to figure this out. We're planning a trip and I'm just completely overwhelmed.\nCustomer Service Agent: I understand, planning a trip can certainly feel that way sometimes. Take a deep breath, I'm here to help gather the details you need. Could you tell me a bit about your trip? For example, where are you planning to go?\nCustomer: Right, yes. Sorry. We're planning a trip to Japan. From Singapore, of course. We're based in Singapore.\nCustomer Service Agent: Okay, Japan. And how many people will be traveling?\nCustomer: There will be 2 of us travelling. Just my spouse and I.\nCustomer Service Agent: Got it, two travelers to Japan. And roughly how long will you be away for?\nCustomer: It will be a 2 weeks trip. Oh god, just thinking about packing… and what if something goes wrong?\nCustomer Service Agent: It's good you're thinking about insurance to cover potential issues. To help find the right fit, could you share the general age group of the travelers?\nCustomer: We're mostly around 41-55 years old.\nCustomer Service Agent: Okay, 41-55 age group. And what sort of activities are you planning during your two weeks in Japan? Anything specific?\nCustomer: Activities... yes, we were hoping… We plan to do Hiking during our trip. Not like, mountain climbing, just some trails. Is… is that covered? If someone twists an ankle or something? That would need the... the sports thing, right? Sports and Adventure Activities coverage?\nCustomer Service Agent: Okay, noted. Hiking. And related to health, are there any pre-existing medical conditions I should be aware of?\nCustomer: Oh, that’s another worry! Yes, one traveler has high blood pressure. Does that… Does that cause problems? We just need cover if, you know, something *unexpected* happens, like a hospital visit for something else entirely. Not routine checks, obviously, but proper Emergency medical treatment. That’s a standard thing, isn't it? Medical Coverage? It's just so stressful worrying about getting sick far from home.\nCustomer Service Agent: I understand the concern. So, noted on the pre-existing condition of high blood pressure and the need for medical coverage for emergencies. Will you be traveling with any special medical equipment?\nCustomer: No, no special medical equipment needed, thankfully. One less thing to worry about, I suppose. But what about… oh dear, what if the airline loses our bags? Or they get damaged? That would be a nightmare. I need to know there's coverage for Lost/Damaged Luggage. The stress would be unbearable.\nCustomer Service Agent: Alright, so coverage for lost or damaged luggage is important for you.\nCustomer: Yes, definitely. And… and flights! What if the flight is delayed for ages? We'd be stuck, need a hotel… It’s so expensive there. We need Travel Delays cover. And worse, what if we have to cancel the whole trip beforehand? Like if one of us gets seriously ill? That's thousands of dollars down the drain... We absolutely need Trip Cancellation cover. This whole process is just making my anxiety worse.\nCustomer Service Agent: Okay, I've noted the requirement for coverage regarding significant travel delays and trip cancellation due to unforeseen covered reasons like illness. Take your time, is there anything else you feel is important for your peace of mind on this trip?\nCustomer: Um… yes, actually. Something specific I read somewhere. It's a bit morbid, I know, but it would make me feel better. I want to know if the policy provides extra coverage, like a double payout, for accidental death if it occurs while traveling on public transport? You know, like if something happens on a bus or a train over there? We’ll be using them a lot. Is that something specific I need to ask for?\nCustomer Service Agent: Okay, I understand. You're specifically asking about a benefit for accidental death that provides a doubled payout if it occurs while on public transportation. I've noted that down. And just to confirm, do you have a budget in mind for the insurance premium?\nCustomer: Oh, budget. Right. We're hoping to spend around $200-$300, if possible. Is that realistic with all this? It's just… so much to think about.\nCustomer Service Agent: Alright, I've noted the budget range as well. Let me quickly summarize the key requirements you've mentioned. You're looking for travel insurance for two adults, aged 41-55, traveling from Singapore to Japan for two weeks. Key coverage needs include: Medical Coverage, considering one traveler has high blood pressure; Trip Cancellation protection; cover for potential Travel Delays; protection for Lost or Damaged Luggage; specific coverage for Hiking under Sports and Adventure Activities; and you specifically require information on whether a policy offers a double payout for accidental death occurring on public transport. Your budget is around $200-$300. Does that sound correct?\nCustomer: Yes… yes, I think that covers everything. It sounds like a lot when you list it like that. Oh dear. But yes, that’s what we need.\nCustomer Service Agent: Thank you for confirming all those details. I have noted down all your requirements. I will pass this information along so we can identify suitable options for you. Someone will be in touch shortly.\nCustomer: Okay. Thank you, Kevin. I… I appreciate your patience.\nCustomer Service Agent: You're welcome. Thank you for calling ISS Insurance Ltd. Have a good day.\nCustomer: You too. Bye.\n",
            "name": null,
            "expected_output": "A JSON object that matches the TravelInsuranceRequirement model.",
            "summary": "Analyze the travel insurance call transcript below and extract key...",
            "raw": "{\n  \"requirement_id\": \"1\",\n  \"requirement_summary\": \"Travel insurance requirement for a trip to Japan.\",\n  \"detailed_description\": \"The customer requires travel insurance for two adults traveling from Singapore to Japan for two weeks. They need coverage for medical emergencies, including a condition of high blood pressure, trip cancellation due to unexpected illness, coverage for travel delays, protection for lost or damaged luggage, and specific coverage for hiking activities. Additionally, they require information on double payout for accidental death occurring on public transport. The budget for the insurance premium is around $200-$300.\",\n  \"travel_origin\": \"Singapore\",\n  \"travel_destination\": \"Japan\",\n  \"travel_duration\": \"2 weeks\",\n  \"insurance_coverage_type\": [\n    \"Medical Coverage\",\n    \"Trip Cancellation\",\n    \"Travel Delays\",\n    \"Lost or Damaged Luggage\",\n    \"Sports and Adventure Activities\"\n  ],\n  \"pre_existing_conditions\": [\n    \"High blood pressure\"\n  ],\n  \"medical_needs\": [\n    \"Emergency medical treatment\"\n  ],\n  \"activities_to_cover\": [\n    \"Hiking\"\n  ],\n  \"age_group\": \"41-55\",\n  \"additional_requests\": \"Double payout for accidental death occurring while using public transport.\",\n  \"keywords\": [\n    \"travel insurance\",\n    \"Japan\",\n    \"medical coverage\",\n    \"trip cancellation\",\n    \"travel delays\",\n    \"lost luggage\",\n    \"hiking\",\n    \"accidental death\",\n    \"public transport\"\n  ]\n}",
            "pydantic": null,
            "json_dict": {
                "requirement_id": "1",
                "requirement_summary": "Travel insurance requirement for a trip to Japan.",
                "detailed_description": "The customer requires travel insurance for two adults traveling from Singapore to Japan for two weeks. They need coverage for medical emergencies, including a condition of high blood pressure, trip cancellation due to unexpected illness, coverage for travel delays, protection for lost or damaged luggage, and specific coverage for hiking activities. Additionally, they require information on double payout for accidental death occurring on public transport. The budget for the insurance premium is around $200-$300.",
                "travel_origin": "Singapore",
                "travel_destination": "Japan",
                "travel_duration": "2 weeks",
                "insurance_coverage_type": [
                    "Medical Coverage",
                    "Trip Cancellation",
                    "Travel Delays",
                    "Lost or Damaged Luggage",
                    "Sports and Adventure Activities"
                ],
                "pre_existing_conditions": [
                    "High blood pressure"
                ],
                "medical_needs": [
                    "Emergency medical treatment"
                ],
                "activities_to_cover": [
                    "Hiking"
                ],
                "age_group": "41-55",
                "additional_requests": "Double payout for accidental death occurring while using public transport.",
                "keywords": [
                    "travel insurance",
                    "Japan",
                    "medical coverage",
                    "trip cancellation",
                    "travel delays",
                    "lost luggage",
                    "hiking",
                    "accidental death",
                    "public transport"
                ]
            },
            "agent": "Call Transcript Analyst",
            "output_format": "json"
        }
    ],
    "token_usage": {
        "total_tokens": 85552,
        "prompt_tokens": 72110,
        "cached_prompt_tokens": 0,
        "completion_tokens": 13442,
        "successful_requests": 46
    }
}