{
    "raw": "{\n  \"requirement_id\": \"1\",\n  \"requirement_summary\": \"Travel insurance needed for a 10-day trip to Australia from Singapore for two travellers aged 41-55.\",\n  \"detailed_description\": \"The customer is seeking travel insurance for a trip to Australia for two people, covering various aspects including medical expenses, trip cancellation, lost or damaged luggage, travel delays, and specific golf-related coverage.\",\n  \"travel_origin\": \"Singapore\",\n  \"travel_destination\": \"Australia\",\n  \"travel_duration\": \"10 days\",\n  \"insurance_coverage_type\": [\n    \"medical coverage overseas\",\n    \"trip cancellation protection\",\n    \"coverage for lost, damaged, or delayed luggage\",\n    \"coverage for travel delays\",\n    \"golf equipment coverage\",\n    \"reimbursement for unused green fees\",\n    \"liability for golf buggy damage\",\n    \"hole-in-one benefits\"\n  ],\n  \"pre_existing_conditions\": [],\n  \"medical_needs\": [],\n  \"activities_to_cover\": [\n    \"golf\",\n    \"sightseeing\"\n  ],\n  \"age_group\": \"41-55\",\n  \"additional_requests\": \"Budget around $200-$300 for insurance.\",\n  \"keywords\": [\n    \"travel insurance\",\n    \"Australia\",\n    \"golf\",\n    \"medical coverage\",\n    \"trip cancellation\",\n    \"luggage coverage\",\n    \"travel delays\"\n  ]\n}",
    "pydantic": null,
    "json_dict": {
        "requirement_id": "1",
        "requirement_summary": "Travel insurance needed for a 10-day trip to Australia from Singapore for two travellers aged 41-55.",
        "detailed_description": "The customer is seeking travel insurance for a trip to Australia for two people, covering various aspects including medical expenses, trip cancellation, lost or damaged luggage, travel delays, and specific golf-related coverage.",
        "travel_origin": "Singapore",
        "travel_destination": "Australia",
        "travel_duration": "10 days",
        "insurance_coverage_type": [
            "medical coverage overseas",
            "trip cancellation protection",
            "coverage for lost, damaged, or delayed luggage",
            "coverage for travel delays",
            "golf equipment coverage",
            "reimbursement for unused green fees",
            "liability for golf buggy damage",
            "hole-in-one benefits"
        ],
        "pre_existing_conditions": [],
        "medical_needs": [],
        "activities_to_cover": [
            "golf",
            "sightseeing"
        ],
        "age_group": "41-55",
        "additional_requests": "Budget around $200-$300 for insurance.",
        "keywords": [
            "travel insurance",
            "Australia",
            "golf",
            "medical coverage",
            "trip cancellation",
            "luggage coverage",
            "travel delays"
        ]
    },
    "tasks_output": [
        {
            "description": "Analyze the travel insurance call transcript below and extract key customer requirements.\nStep 1: Read the transcript carefully and extract all relevant details. For each field in the schema, provide a brief annotation or reference to the specific portion(s) of the transcript where the detail was found.\nStep 2: Review your annotations to verify that every extracted detail directly matches the transcript. Resolve any discrepancies or conflicts in the data.\nStep 3: Produce a final, validated JSON object that adheres exactly to the TravelInsuranceRequirement schema\n\nIf a field is not mentioned in the transcript, use null.\n\nTranscript:\nCustomer Service Agent: Good morning, thank you for calling ISS Insurance Ltd Singapore. My name is Sarah. How may I help you today?\nCustomer: Oh, hello Sarah. Yes, I need to ask about... insurance? For travelling? I'm really quite lost about all this, sorry.\nCustomer Service Agent: Not a problem at all, I can certainly help guide you through gathering what you need. To start, could you tell me where you'll be travelling to?\nCustomer: Yes, we're planning a trip to Australia.\nCustomer Service Agent: Okay, Australia. And how long will you be away for?\nCustomer: We'll be away for 10 days. Leaving from Singapore, of course. We're based in Singapore.\nCustomer Service Agent: Understood, 10 days to Australia, departing from Singapore. And how many people will be travelling?\nCustomer: There will be 2 of us travelling.\nCustomer Service Agent: Alright, two travellers. And roughly, which age group do the travellers fall into? Is it 18-25, 26-40, 41-55, 56-65, or 65+?\nCustomer: Uhm, we're mostly around 41-55 years old.\nCustomer Service Agent: Got it, 41-55 age group. Do you have a budget in mind for the insurance policy?\nCustomer: We're hoping to spend maybe around $200-$300? Is that realistic? I don't really know.\nCustomer Service Agent: Okay, noted the budget range of $200-$300. Now, are there any specific activities you plan to do during your trip? Like any sports or adventure activities?\nCustomer: Activities... well, the main reason we are going is for golf. Lots of golf. Are there... things for golf? I'm a bit worried about my clubs. What if they get lost or broken on the flight? Is that covered?\nCustomer Service Agent: Okay, so cover for golf equipment is something you need information on. Lost or damaged. Noted.\nCustomer: Yes. And, what if, say, I twist my ankle the day before we're supposed to play? We pay for the golf course fees in advance, you see. Can we get that money back if we can't play? The unused green fees?\nCustomer Service Agent: Alright, so you're also asking about reimbursement for unused green fees due to unforeseen circumstances. I've made a note of that.\nCustomer: Yes, exactly. And... oh dear, this sounds silly, but those golf buggies you drive on the course? What happens if I accidentally bump it into something and damage it? It's quite worrying.\nCustomer Service Agent: Understood. So, you need information on coverage related to accidental damage caused to a rented golf buggy.\nCustomer: Yes, please. And one more thing about golf... my friend mentioned some insurance gives a special benefit if you get a hole-in-one? Is that true? It would be amazing, though unlikely for me! But just asking.\nCustomer Service Agent: Okay, so you're also interested in knowing about any available 'hole-in-one' benefits. Noted. Are there any other activities besides golf?\nCustomer: No, no other special activities planned. Just the golf and sightseeing.\nCustomer Service Agent: Okay. Thinking about the trip more generally, what are some other situations you might be concerned about or want protection for?\nCustomer: Oh, um... well, what happens if one of us gets sick while we're in Australia? Like, needing to see a doctor or ending up in hospital? That sounds expensive.\nCustomer Service Agent: Alright, so understanding the coverage for medical expenses incurred overseas, like doctor visits or hospital stays, is important for you.\nCustomer: Yes, definitely. And... sorry to ask so many basic questions... but what if something happens *before* we go? Like, if one of us gets very ill suddenly and we have to cancel the whole holiday? Do we lose all the money we paid?\nCustomer Service Agent: Noted. You need information on coverage regarding trip cancellation due to unforeseen events like illness before departure.\nCustomer: Right. And what about our normal bags, our suitcases? What if the airline loses them, or they arrive days late? It would be terrible to arrive with nothing.\nCustomer Service Agent: Okay, so you're also looking for details on coverage for luggage that is lost, damaged, or delayed by the airline.\nCustomer: Yes. And... uh... flight delays? Sometimes you hear about people getting stuck for a whole day. Does insurance help with... like, needing a hotel room or food if the plane is very, very delayed?\nCustomer Service Agent: Understood. Information regarding coverage for significant travel delays, including expenses like accommodation and meals, is also required.\nCustomer Service Agent: Just a couple more things to ensure we capture everything. Does anyone travelling have any pre-existing medical conditions, like asthma or high blood pressure, that we should be aware of?\nCustomer: Oh, no. No, no pre-existing conditions for either of us.\nCustomer Service Agent: Okay, thank you. And will you be travelling with any special medical equipment, like a wheelchair or CPAP machine?\nCustomer: No, nothing like that needed.\nCustomer Service Agent: Perfect. So, just to quickly summarize what you're looking for information on for your 10-day trip to Australia for two travellers aged 41-55 departing from Singapore, with a budget around $200-$300: You need details on medical coverage overseas, trip cancellation protection, coverage for lost, damaged, or delayed luggage, and help with expenses during significant travel delays. Specifically related to golf, you need information on coverage for golf equipment, reimbursement for unused green fees, liability for golf buggy damage, and potential hole-in-one benefits. Does that sound correct?\nCustomer: Yes, I think... I think that's everything. It sounds like a lot when you say it like that! Sorry if I was confusing.\nCustomer Service Agent: Not at all, you were very clear. Thank you for providing all those details. That gives us a good understanding of the information you require. I have recorded these requirements.\nCustomer: Okay, good. Thank you for your patience, Sarah.\nCustomer Service Agent: You're most welcome. Thank you for calling ISS Insurance Ltd. Have a great day!\nCustomer: You too. Bye bye.\n",
            "name": null,
            "expected_output": "A JSON object that matches the TravelInsuranceRequirement model.",
            "summary": "Analyze the travel insurance call transcript below and extract key...",
            "raw": "{\n  \"requirement_id\": \"1\",\n  \"requirement_summary\": \"Travel insurance needed for a 10-day trip to Australia from Singapore for two travellers aged 41-55.\",\n  \"detailed_description\": \"The customer is seeking travel insurance for a trip to Australia for two people, covering various aspects including medical expenses, trip cancellation, lost or damaged luggage, travel delays, and specific golf-related coverage.\",\n  \"travel_origin\": \"Singapore\",\n  \"travel_destination\": \"Australia\",\n  \"travel_duration\": \"10 days\",\n  \"insurance_coverage_type\": [\n    \"medical coverage overseas\",\n    \"trip cancellation protection\",\n    \"coverage for lost, damaged, or delayed luggage\",\n    \"coverage for travel delays\",\n    \"golf equipment coverage\",\n    \"reimbursement for unused green fees\",\n    \"liability for golf buggy damage\",\n    \"hole-in-one benefits\"\n  ],\n  \"pre_existing_conditions\": [],\n  \"medical_needs\": [],\n  \"activities_to_cover\": [\n    \"golf\",\n    \"sightseeing\"\n  ],\n  \"age_group\": \"41-55\",\n  \"additional_requests\": \"Budget around $200-$300 for insurance.\",\n  \"keywords\": [\n    \"travel insurance\",\n    \"Australia\",\n    \"golf\",\n    \"medical coverage\",\n    \"trip cancellation\",\n    \"luggage coverage\",\n    \"travel delays\"\n  ]\n}",
            "pydantic": null,
            "json_dict": {
                "requirement_id": "1",
                "requirement_summary": "Travel insurance needed for a 10-day trip to Australia from Singapore for two travellers aged 41-55.",
                "detailed_description": "The customer is seeking travel insurance for a trip to Australia for two people, covering various aspects including medical expenses, trip cancellation, lost or damaged luggage, travel delays, and specific golf-related coverage.",
                "travel_origin": "Singapore",
                "travel_destination": "Australia",
                "travel_duration": "10 days",
                "insurance_coverage_type": [
                    "medical coverage overseas",
                    "trip cancellation protection",
                    "coverage for lost, damaged, or delayed luggage",
                    "coverage for travel delays",
                    "golf equipment coverage",
                    "reimbursement for unused green fees",
                    "liability for golf buggy damage",
                    "hole-in-one benefits"
                ],
                "pre_existing_conditions": [],
                "medical_needs": [],
                "activities_to_cover": [
                    "golf",
                    "sightseeing"
                ],
                "age_group": "41-55",
                "additional_requests": "Budget around $200-$300 for insurance.",
                "keywords": [
                    "travel insurance",
                    "Australia",
                    "golf",
                    "medical coverage",
                    "trip cancellation",
                    "luggage coverage",
                    "travel delays"
                ]
            },
            "agent": "Call Transcript Analyst",
            "output_format": "json"
        }
    ],
    "token_usage": {
        "total_tokens": 4093,
        "prompt_tokens": 3516,
        "cached_prompt_tokens": 0,
        "completion_tokens": 577,
        "successful_requests": 2
    }
}