{
    "raw": "{\n  \"requirement_id\": \"req-001\",\n  \"requirement_summary\": \"Travel insurance for a 2-week trip to Japan for two adults aged 26-40, covering medical expenses, trip cancellation, travel delays, lost luggage, sports activities, and political unrest.\",\n  \"detailed_description\": \"The customer is looking for travel insurance for a 2-week trip to Japan. They require cover for medical emergencies due to potential illness, including an existing condition (asthma) of one traveler. There are concerns about needing to cancel the trip due to a family emergency, and they seek protection against travel delays that could incur extra costs. The customer is also interested in coverage for lost or damaged luggage, and specifically for injuries during skiing, an adventurous activity they plan to try. Additionally, they want to ensure they are covered regarding political unrest or unforeseen events occurring in Japan during their stay. They have a budget preference of $200-$300 for this insurance.\",\n  \"travel_destination\": \"Japan\",\n  \"travel_duration\": \"2 weeks\",\n  \"travel_start_date\": null,\n  \"travel_end_date\": null,\n  \"insurance_coverage_type\": [\n    \"Medical Expenses\",\n    \"Trip Cancellation\",\n    \"Travel Delays\",\n    \"Lost or Damaged Luggage\",\n    \"Sports and Adventure Activities\",\n    \"War or Political Unrest\"\n  ],\n  \"pre_existing_conditions\": [\n    \"Asthma\"\n  ],\n  \"age_group\": \"26-40\",\n  \"travelers_count\": 2,\n  \"traveler_details\": [\n    {\n      \"age\": null,\n      \"gender\": null,\n      \"citizenship\": null\n    },\n    {\n      \"age\": null,\n      \"gender\": null,\n      \"citizenship\": null\n    }\n  ],\n  \"budget_range\": \"$200-$300\",\n  \"preferred_insurance_provider\": null,\n  \"additional_requests\": null,\n  \"keywords\": [\n    \"Japan\",\n    \"travel insurance\",\n    \"medical coverage\",\n    \"trip cancellation\",\n    \"travel delays\",\n    \"lost luggage\",\n    \"skiing\",\n    \"political unrest\"\n  ]\n}",
    "pydantic": null,
    "json_dict": {
        "requirement_id": "req-001",
        "requirement_summary": "Travel insurance for a 2-week trip to Japan for two adults aged 26-40, covering medical expenses, trip cancellation, travel delays, lost luggage, sports activities, and political unrest.",
        "detailed_description": "The customer is looking for travel insurance for a 2-week trip to Japan. They require cover for medical emergencies due to potential illness, including an existing condition (asthma) of one traveler. There are concerns about needing to cancel the trip due to a family emergency, and they seek protection against travel delays that could incur extra costs. The customer is also interested in coverage for lost or damaged luggage, and specifically for injuries during skiing, an adventurous activity they plan to try. Additionally, they want to ensure they are covered regarding political unrest or unforeseen events occurring in Japan during their stay. They have a budget preference of $200-$300 for this insurance.",
        "travel_destination": "Japan",
        "travel_duration": "2 weeks",
        "travel_start_date": null,
        "travel_end_date": null,
        "insurance_coverage_type": [
            "Medical Expenses",
            "Trip Cancellation",
            "Travel Delays",
            "Lost or Damaged Luggage",
            "Sports and Adventure Activities",
            "War or Political Unrest"
        ],
        "pre_existing_conditions": [
            "Asthma"
        ],
        "age_group": "26-40",
        "travelers_count": 2,
        "traveler_details": [
            {
                "age": null,
                "gender": null,
                "citizenship": null
            },
            {
                "age": null,
                "gender": null,
                "citizenship": null
            }
        ],
        "budget_range": "$200-$300",
        "preferred_insurance_provider": null,
        "additional_requests": null,
        "keywords": [
            "Japan",
            "travel insurance",
            "medical coverage",
            "trip cancellation",
            "travel delays",
            "lost luggage",
            "skiing",
            "political unrest"
        ]
    },
    "tasks_output": [
        {
            "description": "Analyze the travel insurance call transcript below and extract key customer requirements.\nStep 1: Read the transcript carefully and extract all relevant details. For each field in the schema, provide a brief annotation or reference to the specific portion(s) of the transcript where the detail was found.\nStep 2: Review your annotations to verify that every extracted detail directly matches the transcript. Resolve any discrepancies or conflicts in the data.\nStep 3: Produce a final, validated JSON object that adheres exactly to the TravelInsuranceRequirement schema with the following fields:\n- requirement_id (str): A unique identifier.\n- requirement_summary (str): A concise summary of the customer's insurance needs.\n- detailed_description (str): A detailed narrative extracted from the transcript.\n- travel_destination (Optional[str]): The destination (country or region) mentioned.\n- travel_duration (Optional[str]): Duration of the trip (e.g., \"7 days\", \"1 month\").\n- travel_start_date (Optional[date]): The travel start date.\n- travel_end_date (Optional[date]): The travel end date.\n- insurance_coverage_type (Optional[List[str]]): The types of insurance coverage requested (e.g., [\"Medical\", \"Trip Cancellation\"]).\n- pre_existing_conditions (Optional[List[str]]): Any pre-existing conditions mentioned.\n- age_group (Optional[str]): Age bracket of the travelers (e.g., \"26-40\").\n- travelers_count (Optional[int]): Number of travelers.\n- budget_range (Optional[str]): Budget constraints (e.g., \"$100-$200\").\n- preferred_insurance_provider (Optional[str]): Preferred insurance provider, if any.\n- additional_requests (Optional[str]): Any special requests or concerns.\n- keywords (Optional[List[str]]): Important keywords or terms for further analysis.\n\nIf a field is not mentioned in the transcript, use null.\n\nTranscript:\nCustomer Service Agent: Good morning, thank you for calling ISS Insurance Ltd Singapore. My name is Sarah, how may I help you today?\nCustomer: Oh, hello Sarah. Yes, um, I need to ask about... insurance? For travelling. I've never bought this before, I'm a bit lost, sorry.\nCustomer Service Agent: Not a problem at all, I can certainly help guide you through the process of getting a quote. To start, could you tell me a bit about your trip? Where are you planning to go?\nCustomer: Yes, yes. We're planning a trip to Japan.\nCustomer Service Agent: Japan, lovely! And how long will you be away for?\nCustomer: It will be a 2 weeks trip. Quite long for us!\nCustomer Service Agent: Okay, two weeks in Japan. And how many people will be travelling?\nCustomer: There will be 2 of us traveling. Me and my husband.\nCustomer Service Agent: Got it, two travellers. And may I know which age group you both fall into? Is it 18-25, 26-40, 41-55, 56-65, or 65+?\nCustomer: Oh, um. We're mostly around 26-40 years old. Both of us.\nCustomer Service Agent: Perfect, thank you. Now, thinking about the trip, what sort of things are you concerned about or want to make sure you have cover for?\nCustomer: Erm... well, everything? I don't know. Like, what if we get sick there? You know, need to see a doctor or... worse, end up in hospital? That sounds expensive.\nCustomer Service Agent: Okay, so cover for medical emergencies is important for you. Noted. Are there any other health considerations? For example, do we need to declare asthma for one traveler?\nCustomer: Oh! Yes, my husband has asthma. Is that... okay? Does it make things complicated? Sorry, I don't understand this part.\nCustomer Service Agent: No need to apologize at all! It's good you mentioned it. We just need to note it down. So, medical cover, noting the asthma. What else comes to mind?\nCustomer: Well... before the trip even starts... what if something happens? Like, if my mother gets really sick suddenly and we can't go? We've paid for flights and hotels... do we just lose all that money?\nCustomer Service Agent: Alright, so you're concerned about situations that might force you to cancel the trip beforehand for reasons like family emergencies. I'll note that down as needing cover for trip cancellation.\nCustomer: Yes, exactly! And... flights. Sometimes they get delayed, right? I saw it on the news. What if our flight is stuck for hours and hours? We might miss our connecting flight in Japan, or need a hotel overnight? Does insurance help with that?\nCustomer Service Agent: Okay, so you're also interested in cover for significant travel delays that might cause extra expenses for accommodation or meals.\nCustomer: Yes! That would be good. Oh, and bags! Luggage! What if the airline loses our suitcases? Or if my suitcase gets broken on the way? That would be terrible.\nCustomer Service Agent: Understood. So cover for lost, damaged, or delayed baggage is another point you'd like included.\nCustomer: Yes please. Hmm, what else... Oh! We were hoping to try skiing in Japan! Just for fun, you know, beginners. But... what if one of us falls and gets hurt doing that? Is that covered by the normal medical thing, or is it separate because it's... adventurous? I'm confused.\nCustomer Service Agent: That's a very good question. Activities like skiing often need specific mention. So you'd like cover for potential injuries while participating in sports or adventure activities, specifically skiing.\nCustomer: Yes, if possible. It sounds scary otherwise. Um... one more thing, maybe it sounds silly... Japan is very safe, I know, but... sometimes you hear about things happening in the world. Like, big protests, or... worse? What if something like... a war or big political problem started while we were there? Is there anything for... that kind of situation? Like getting out?\nCustomer Service Agent: Okay, so you're asking about cover related to unforeseen events like acts of war or political unrest occurring in your destination during your trip. I'll make a note of that concern as well.\nCustomer Service Agent: Thank you for sharing all that. It helps us understand what's important for your peace of mind. Do you have a budget in mind for the insurance premium? We have options ranging from $100-$200, $200-$300, around $400, or flexible.\nCustomer: Oh, budget... hmm. We're hoping to spend maybe $200-$300 if possible? Is that realistic for all these things? Sorry, I really have no idea.\nCustomer Service Agent: Thank you, noting the budget preference of $200-$300. Okay, let me just quickly summarize what I've noted down based on our chat. You're looking for travel insurance for two adults, aged 26-40, travelling to Japan for two weeks. You require information on cover for: Medical Expenses, including noting one traveller has asthma; Trip Cancellation; Travel Delays; Lost or Damaged Luggage; Sports and Adventure activities, specifically skiing; and potential assistance related to War or Political Unrest. And you have a preferred budget of around $200-$300. Does that sound correct?\nCustomer: Yes, I think so. Wow, that's a lot of things. I didn't realise there were so many parts to it. Yes, that covers what I was worried about. Thank you for being patient, I know I asked basic things.\nCustomer Service Agent: Not at all, it's important to understand your needs clearly. Thank you for providing all the details. I have recorded your requirements. The next step would be for our team to generate specific quotes based on this information. Would you like me to proceed with submitting this request for quotation?\nCustomer: Oh, yes please. That would be great. Thank you, Sarah.\nCustomer Service Agent: You're welcome. We will get the quotes prepared and sent to your email address shortly. Thank you for calling ISS Insurance Ltd. Have a great day!\nCustomer: Thank you! You too. Bye bye.\n",
            "name": null,
            "expected_output": "A JSON object that matches the TravelInsuranceRequirement model.",
            "summary": "Analyze the travel insurance call transcript below and extract key...",
            "raw": "{\n  \"requirement_id\": \"req-001\",\n  \"requirement_summary\": \"Travel insurance for a 2-week trip to Japan for two adults aged 26-40, covering medical expenses, trip cancellation, travel delays, lost luggage, sports activities, and political unrest.\",\n  \"detailed_description\": \"The customer is looking for travel insurance for a 2-week trip to Japan. They require cover for medical emergencies due to potential illness, including an existing condition (asthma) of one traveler. There are concerns about needing to cancel the trip due to a family emergency, and they seek protection against travel delays that could incur extra costs. The customer is also interested in coverage for lost or damaged luggage, and specifically for injuries during skiing, an adventurous activity they plan to try. Additionally, they want to ensure they are covered regarding political unrest or unforeseen events occurring in Japan during their stay. They have a budget preference of $200-$300 for this insurance.\",\n  \"travel_destination\": \"Japan\",\n  \"travel_duration\": \"2 weeks\",\n  \"travel_start_date\": null,\n  \"travel_end_date\": null,\n  \"insurance_coverage_type\": [\n    \"Medical Expenses\",\n    \"Trip Cancellation\",\n    \"Travel Delays\",\n    \"Lost or Damaged Luggage\",\n    \"Sports and Adventure Activities\",\n    \"War or Political Unrest\"\n  ],\n  \"pre_existing_conditions\": [\n    \"Asthma\"\n  ],\n  \"age_group\": \"26-40\",\n  \"travelers_count\": 2,\n  \"traveler_details\": [\n    {\n      \"age\": null,\n      \"gender\": null,\n      \"citizenship\": null\n    },\n    {\n      \"age\": null,\n      \"gender\": null,\n      \"citizenship\": null\n    }\n  ],\n  \"budget_range\": \"$200-$300\",\n  \"preferred_insurance_provider\": null,\n  \"additional_requests\": null,\n  \"keywords\": [\n    \"Japan\",\n    \"travel insurance\",\n    \"medical coverage\",\n    \"trip cancellation\",\n    \"travel delays\",\n    \"lost luggage\",\n    \"skiing\",\n    \"political unrest\"\n  ]\n}",
            "pydantic": null,
            "json_dict": {
                "requirement_id": "req-001",
                "requirement_summary": "Travel insurance for a 2-week trip to Japan for two adults aged 26-40, covering medical expenses, trip cancellation, travel delays, lost luggage, sports activities, and political unrest.",
                "detailed_description": "The customer is looking for travel insurance for a 2-week trip to Japan. They require cover for medical emergencies due to potential illness, including an existing condition (asthma) of one traveler. There are concerns about needing to cancel the trip due to a family emergency, and they seek protection against travel delays that could incur extra costs. The customer is also interested in coverage for lost or damaged luggage, and specifically for injuries during skiing, an adventurous activity they plan to try. Additionally, they want to ensure they are covered regarding political unrest or unforeseen events occurring in Japan during their stay. They have a budget preference of $200-$300 for this insurance.",
                "travel_destination": "Japan",
                "travel_duration": "2 weeks",
                "travel_start_date": null,
                "travel_end_date": null,
                "insurance_coverage_type": [
                    "Medical Expenses",
                    "Trip Cancellation",
                    "Travel Delays",
                    "Lost or Damaged Luggage",
                    "Sports and Adventure Activities",
                    "War or Political Unrest"
                ],
                "pre_existing_conditions": [
                    "Asthma"
                ],
                "age_group": "26-40",
                "travelers_count": 2,
                "traveler_details": [
                    {
                        "age": null,
                        "gender": null,
                        "citizenship": null
                    },
                    {
                        "age": null,
                        "gender": null,
                        "citizenship": null
                    }
                ],
                "budget_range": "$200-$300",
                "preferred_insurance_provider": null,
                "additional_requests": null,
                "keywords": [
                    "Japan",
                    "travel insurance",
                    "medical coverage",
                    "trip cancellation",
                    "travel delays",
                    "lost luggage",
                    "skiing",
                    "political unrest"
                ]
            },
            "agent": "Call Transcript Analyst",
            "output_format": "json"
        }
    ],
    "token_usage": {
        "total_tokens": 2527,
        "prompt_tokens": 2071,
        "cached_prompt_tokens": 0,
        "completion_tokens": 456,
        "successful_requests": 1
    }
}