{
    "raw": "{\n  \"requirement_id\": \"REQ12345\",\n  \"requirement_summary\": \"Travel insurance coverage for a trip from Singapore to Japan.\",\n  \"detailed_description\": \"The customer is planning a 2-week trip from Singapore to Japan with concerns about trip cancellation, medical expenses due to pre-existing asthma, lost/damaged/delayed luggage, travel delays, hiking injuries, and extra coverage for accidental death on public transport. The budget for the insurance is around $400.\",\n  \"travel_origin\": \"Singapore\",\n  \"travel_destination\": \"Japan\",\n  \"travel_duration\": \"2 weeks\",\n  \"insurance_coverage_type\": [\n    \"Trip Cancellation\",\n    \"Medical Expenses\",\n    \"Lost/Damaged/Delayed Luggage\",\n    \"Travel Delay\",\n    \"Hiking Injuries\",\n    \"Accidental Death on Public Transport\"\n  ],\n  \"pre_existing_conditions\": [\n    \"Asthma\"\n  ],\n  \"medical_needs\": [\n    \"Inhaler\"\n  ],\n  \"activities_to_cover\": [\n    \"Hiking\"\n  ],\n  \"age_group\": \"26-40\",\n  \"additional_requests\": \"Double payout for accidental death while using public transportation.\",\n  \"keywords\": [\n    \"insurance\",\n    \"travel\",\n    \"cancellation\",\n    \"medical\",\n    \"luggage\",\n    \"delays\",\n    \"hiking\",\n    \"accidental death\",\n    \"public transport\"\n  ]\n}",
    "pydantic": null,
    "json_dict": {
        "requirement_id": "REQ12345",
        "requirement_summary": "Travel insurance coverage for a trip from Singapore to Japan.",
        "detailed_description": "The customer is planning a 2-week trip from Singapore to Japan with concerns about trip cancellation, medical expenses due to pre-existing asthma, lost/damaged/delayed luggage, travel delays, hiking injuries, and extra coverage for accidental death on public transport. The budget for the insurance is around $400.",
        "travel_origin": "Singapore",
        "travel_destination": "Japan",
        "travel_duration": "2 weeks",
        "insurance_coverage_type": [
            "Trip Cancellation",
            "Medical Expenses",
            "Lost/Damaged/Delayed Luggage",
            "Travel Delay",
            "Hiking Injuries",
            "Accidental Death on Public Transport"
        ],
        "pre_existing_conditions": [
            "Asthma"
        ],
        "medical_needs": [
            "Inhaler"
        ],
        "activities_to_cover": [
            "Hiking"
        ],
        "age_group": "26-40",
        "additional_requests": "Double payout for accidental death while using public transportation.",
        "keywords": [
            "insurance",
            "travel",
            "cancellation",
            "medical",
            "luggage",
            "delays",
            "hiking",
            "accidental death",
            "public transport"
        ]
    },
    "tasks_output": [
        {
            "description": "Analyze the travel insurance call transcript below and extract key customer requirements.\nStep 1: Read the transcript carefully and extract all relevant details. For each field in the schema, provide a brief annotation or reference to the specific portion(s) of the transcript where the detail was found.\nStep 2: Review your annotations to verify that every extracted detail directly matches the transcript. Resolve any discrepancies or conflicts in the data.\nStep 3: Produce a final, validated JSON object that adheres exactly to the TravelInsuranceRequirement schema\n\nIf a field is not mentioned in the transcript, use null.\n\nTranscript:\nCustomer Service Agent: Thank you for calling ISS Insurance Ltd. My name is Sarah. How may I help you today?\nCustomer: Oh, hello? Sarah? Yes, hi. I... I need to ask about travel insurance. I'm planning a trip and it's... it's all a bit much, honestly. So many things to think about, I don't know where to start. I'm already feeling quite stressed.\nCustomer Service Agent: I understand travelling can feel overwhelming, don't worry. I can help you figure out what details we need. Take a deep breath, we'll go through it step by step. Could you start by telling me where you'll be travelling from?\nCustomer: Yes, yes, okay. Deep breath. We're based in Singapore, so traveling from Singapore.\nCustomer Service Agent: Okay, noted. And where are you planning to travel to?\nCustomer: We're planning a trip to Japan. It's supposed to be relaxing but planning is just... argh.\nCustomer Service Agent: Japan is a popular choice. And how long will you be away for?\nCustomer: It will be a 2 weeks trip. Just... feels like so much could go wrong in two weeks, you know? What if something happens before we even go? Like, if one of us gets sick or there's a family emergency? We'd lose all the money we paid... it's terrifying.\nCustomer Service Agent: Okay, so you're concerned about the possibility of having to cancel the trip beforehand due to unforeseen circumstances like illness or family emergencies and losing your deposits?\nCustomer: Exactly! Yes, that's a big worry. Cancellation coverage is definitely something... something I need to understand.\nCustomer Service Agent: Understood. And how many people will be travelling?\nCustomer: There will be 2 of us traveling. Just my partner and I.\nCustomer Service Agent: Alright. And roughly, what age group do the travellers fall into?\nCustomer: We're mostly around 26-40 years old.\nCustomer Service Agent: Got it. Now, thinking about the trip itself, are there any specific health concerns or conditions we should be aware of? Perhaps any pre-existing conditions?\nCustomer: Well, I have asthma. It's managed, but you know, different environment... different air... Do we need to declare asthma? It just adds another layer of worry, getting sick so far from home. What if I have an attack? Need a doctor? Or end up in hospital? The cost... oh god.\nCustomer Service Agent: Okay, noted about the asthma and your concern regarding potential medical expenses overseas, like doctor visits or hospital stays. We'll factor that in. Are there any specific medical equipment you need to bring, like a wheelchair or CPAP machine?\nCustomer: Oh, no, no. Thankfully no special medical equipment needed. Just my inhaler.\nCustomer Service Agent: Understood. How about your luggage? Any specific concerns there?\nCustomer: Luggage? Oh, don't get me started. Last time we flew, the airline lost my bag for three days! It was a nightmare. I had nothing. So yes, definitely need something for lost luggage... or if it gets damaged or delayed again. It's just so stressful when your things go missing.\nCustomer Service Agent: Alright, so coverage for lost, damaged, or delayed baggage is important for you, including reimbursement for essentials if it's delayed. Noted. What about travel disruptions during the trip?\nCustomer: Like what? You mean... flights being delayed? Oh yes, definitely. Getting stuck somewhere, needing extra hotel nights, food... the cost adds up so fast. That's incredibly stressful thinking about that possibility. So cover for travel delays is important too.\nCustomer Service Agent: Okay, cover for additional expenses due to significant travel delays. And will you be participating in any specific sports or adventure activities during your trip to Japan?\nCustomer: Oh, umm... we were thinking of doing some hiking. Nothing too extreme, just some trails. But what if someone twists an ankle or something? Does that count? We need coverage for hiking, I suppose. It feels risky just thinking about it now...\nCustomer Service Agent: Understood, coverage for injuries related to participation in hiking. Thank you for clarifying. Do you have a budget in mind for the insurance premium?\nCustomer: Budget... hmm. We're hoping to spend around $400 for the insurance for both of us, if possible. But peace of mind is key.\nCustomer Service Agent: Okay, noted the budget preference. Is there anything else specific you're looking for or concerned about?\nCustomer: Yes, actually. I was reading something... I want to know if the policy provides extra coverage if an accident happens while I'm on a bus or train? Like, a really serious accident, god forbid. Does the payout double for accidental death if it occurs while traveling on public transport? It sounds morbid, but these things... they worry me.\nCustomer Service Agent: Okay, thank you for bringing that up. You're specifically asking about a feature that provides a double payout for accidental death if it happens while using public transportation like buses or trains. I've noted that requirement.\nCustomer Service Agent: Alright, let me just quickly recap the requirements you've mentioned to ensure I've captured everything correctly. You're travelling from Singapore to Japan for 2 weeks, there are two travellers aged 26-40. You require coverage for: Trip Cancellation, potential Medical Expenses overseas (noting pre-existing asthma), Lost/Damaged/Delayed Luggage, significant Travel Delays, injuries related to Hiking activities, and you specifically want the policy to include a Double Payout for Accidental Death occurring on Public Transport. Your budget is around $400. Does that sound correct?\nCustomer: Yes... yes, I think that's everything. Hearing it listed out makes it slightly less... chaotic in my head. Hiking, luggage, delays, medical, cancellation... and the public transport thing. Yes, that's it. Thank you for being patient.\nCustomer Service Agent: You're most welcome. I'm glad I could help clarify things. I have gathered all the necessary details regarding your requirements now. The next step would be for our sales team to use this information to find suitable policy options for you. Would you like me to arrange for them to contact you?\nCustomer: Oh, okay. Yes please. That would be good. Thank you, Sarah.\nCustomer Service Agent: You're welcome. Thank you for calling ISS Insurance. Have a good day.\nCustomer: You too. Bye.\n",
            "name": null,
            "expected_output": "A JSON object that matches the TravelInsuranceRequirement model.",
            "summary": "Analyze the travel insurance call transcript below and extract key...",
            "raw": "{\n  \"requirement_id\": \"REQ12345\",\n  \"requirement_summary\": \"Travel insurance coverage for a trip from Singapore to Japan.\",\n  \"detailed_description\": \"The customer is planning a 2-week trip from Singapore to Japan with concerns about trip cancellation, medical expenses due to pre-existing asthma, lost/damaged/delayed luggage, travel delays, hiking injuries, and extra coverage for accidental death on public transport. The budget for the insurance is around $400.\",\n  \"travel_origin\": \"Singapore\",\n  \"travel_destination\": \"Japan\",\n  \"travel_duration\": \"2 weeks\",\n  \"insurance_coverage_type\": [\n    \"Trip Cancellation\",\n    \"Medical Expenses\",\n    \"Lost/Damaged/Delayed Luggage\",\n    \"Travel Delay\",\n    \"Hiking Injuries\",\n    \"Accidental Death on Public Transport\"\n  ],\n  \"pre_existing_conditions\": [\n    \"Asthma\"\n  ],\n  \"medical_needs\": [\n    \"Inhaler\"\n  ],\n  \"activities_to_cover\": [\n    \"Hiking\"\n  ],\n  \"age_group\": \"26-40\",\n  \"additional_requests\": \"Double payout for accidental death while using public transportation.\",\n  \"keywords\": [\n    \"insurance\",\n    \"travel\",\n    \"cancellation\",\n    \"medical\",\n    \"luggage\",\n    \"delays\",\n    \"hiking\",\n    \"accidental death\",\n    \"public transport\"\n  ]\n}",
            "pydantic": null,
            "json_dict": {
                "requirement_id": "REQ12345",
                "requirement_summary": "Travel insurance coverage for a trip from Singapore to Japan.",
                "detailed_description": "The customer is planning a 2-week trip from Singapore to Japan with concerns about trip cancellation, medical expenses due to pre-existing asthma, lost/damaged/delayed luggage, travel delays, hiking injuries, and extra coverage for accidental death on public transport. The budget for the insurance is around $400.",
                "travel_origin": "Singapore",
                "travel_destination": "Japan",
                "travel_duration": "2 weeks",
                "insurance_coverage_type": [
                    "Trip Cancellation",
                    "Medical Expenses",
                    "Lost/Damaged/Delayed Luggage",
                    "Travel Delay",
                    "Hiking Injuries",
                    "Accidental Death on Public Transport"
                ],
                "pre_existing_conditions": [
                    "Asthma"
                ],
                "medical_needs": [
                    "Inhaler"
                ],
                "activities_to_cover": [
                    "Hiking"
                ],
                "age_group": "26-40",
                "additional_requests": "Double payout for accidental death while using public transportation.",
                "keywords": [
                    "insurance",
                    "travel",
                    "cancellation",
                    "medical",
                    "luggage",
                    "delays",
                    "hiking",
                    "accidental death",
                    "public transport"
                ]
            },
            "agent": "Call Transcript Analyst",
            "output_format": "json"
        }
    ],
    "token_usage": {
        "total_tokens": 95137,
        "prompt_tokens": 80272,
        "cached_prompt_tokens": 0,
        "completion_tokens": 14865,
        "successful_requests": 51
    }
}