{
    "raw": "{\n  \"requirement_id\": \"req_001\",\n  \"requirement_summary\": \"Travel insurance needed for a two-week trip to Japan for two travelers, including coverage for trip cancellation, medical expenses, skiing activities, travel delays, luggage, and political unrest.\",\n  \"detailed_description\": \"The customer is planning a trip to Japan for two weeks and requires travel insurance due to concerns about potential trip cancellations (e.g., sickness or family emergencies), medical coverage for one traveler with high blood pressure, coverage for skiing activities, coverage for significant travel delays, lost or damaged luggage, and insurance against war and political unrest. The travelers are aged 26-40, and they are budgeting around $400 for their insurance policy.\",\n  \"travel_destination\": \"Japan\",\n  \"travel_duration\": \"2 weeks\",\n  \"travel_start_date\": null,\n  \"travel_end_date\": null,\n  \"insurance_coverage_type\": [\n    \"Trip Cancellation\",\n    \"Medical Coverage\",\n    \"Sports and Adventure Activities\",\n    \"Travel Delays\",\n    \"Lost or Damaged Luggage\",\n    \"War and Political Unrest\"\n  ],\n  \"pre_existing_conditions\": [\n    \"High Blood Pressure\"\n  ],\n  \"age_group\": \"26-40\",\n  \"travelers_count\": 2,\n  \"traveler_details\": null,\n  \"budget_range\": \"$400\",\n  \"preferred_insurance_provider\": null,\n  \"additional_requests\": null,\n  \"keywords\": [\n    \"Travel Insurance\",\n    \"Japan\",\n    \"Trip Cancellation\",\n    \"Medical Coverage\",\n    \"Skiing\",\n    \"Travel Delays\",\n    \"Luggage\",\n    \"Political Unrest\"\n  ]\n}",
    "pydantic": null,
    "json_dict": {
        "requirement_id": "req_001",
        "requirement_summary": "Travel insurance needed for a two-week trip to Japan for two travelers, including coverage for trip cancellation, medical expenses, skiing activities, travel delays, luggage, and political unrest.",
        "detailed_description": "The customer is planning a trip to Japan for two weeks and requires travel insurance due to concerns about potential trip cancellations (e.g., sickness or family emergencies), medical coverage for one traveler with high blood pressure, coverage for skiing activities, coverage for significant travel delays, lost or damaged luggage, and insurance against war and political unrest. The travelers are aged 26-40, and they are budgeting around $400 for their insurance policy.",
        "travel_destination": "Japan",
        "travel_duration": "2 weeks",
        "travel_start_date": null,
        "travel_end_date": null,
        "insurance_coverage_type": [
            "Trip Cancellation",
            "Medical Coverage",
            "Sports and Adventure Activities",
            "Travel Delays",
            "Lost or Damaged Luggage",
            "War and Political Unrest"
        ],
        "pre_existing_conditions": [
            "High Blood Pressure"
        ],
        "age_group": "26-40",
        "travelers_count": 2,
        "traveler_details": null,
        "budget_range": "$400",
        "preferred_insurance_provider": null,
        "additional_requests": null,
        "keywords": [
            "Travel Insurance",
            "Japan",
            "Trip Cancellation",
            "Medical Coverage",
            "Skiing",
            "Travel Delays",
            "Luggage",
            "Political Unrest"
        ]
    },
    "tasks_output": [
        {
            "description": "Analyze the travel insurance call transcript below and extract key customer requirements.\nStep 1: Read the transcript carefully and extract all relevant details. For each field in the schema, provide a brief annotation or reference to the specific portion(s) of the transcript where the detail was found.\nStep 2: Review your annotations to verify that every extracted detail directly matches the transcript. Resolve any discrepancies or conflicts in the data.\nStep 3: Produce a final, validated JSON object that adheres exactly to the TravelInsuranceRequirement schema with the following fields:\n- requirement_id (str): A unique identifier.\n- requirement_summary (str): A concise summary of the customer's insurance needs.\n- detailed_description (str): A detailed narrative extracted from the transcript.\n- travel_destination (Optional[str]): The destination (country or region) mentioned.\n- travel_duration (Optional[str]): Duration of the trip (e.g., \"7 days\", \"1 month\").\n- travel_start_date (Optional[date]): The travel start date.\n- travel_end_date (Optional[date]): The travel end date.\n- insurance_coverage_type (Optional[List[str]]): The types of insurance coverage requested (e.g., [\"Medical\", \"Trip Cancellation\"]).\n- pre_existing_conditions (Optional[List[str]]): Any pre-existing conditions mentioned.\n- age_group (Optional[str]): Age bracket of the travelers (e.g., \"26-40\").\n- travelers_count (Optional[int]): Number of travelers.\n- budget_range (Optional[str]): Budget constraints (e.g., \"$100-$200\").\n- preferred_insurance_provider (Optional[str]): Preferred insurance provider, if any.\n- additional_requests (Optional[str]): Any special requests or concerns.\n- keywords (Optional[List[str]]): Important keywords or terms for further analysis.\n\nIf a field is not mentioned in the transcript, use null.\n\nTranscript:\nCustomer Service Agent: Good morning, thank you for calling ISS Insurance Ltd Singapore. My name is Sarah, how may I assist you today?\nCustomer: Oh, hello? Yes, hi Sarah. I... I need help. I'm trying to figure out travel insurance and it's all just... so much. I'm planning a trip and I'm already feeling completely stressed out about everything that could go wrong. It's overwhelming.\nCustomer Service Agent: I understand getting insurance can feel like a lot, but I'm here to help gather the details we need. Take a deep breath, we can go through this step by step. Could you tell me a bit about your trip? For example, where are you planning to travel to?\nCustomer: Okay, okay, deep breath. Right. We're planning a trip to Japan. Just trying to get everything sorted is... yeah.\nCustomer Service Agent: Japan, lovely. And how long will you be away for?\nCustomer: It will be a 2 weeks trip. But what if... what if something happens *before* we even go? Like, if one of us gets sick, or there's a family emergency? We'd lose so much money. The thought is making me panic. We definitely need cover if we have to cancel the whole thing for a serious reason. That's a big worry.\nCustomer Service Agent: Okay, I understand the concern about needing to cancel the trip beforehand. Noted. And how many people will be travelling on this policy?\nCustomer: There will be 2 of us traveling.\nCustomer Service Agent: Alright, two travellers going to Japan for two weeks. And roughly, which age group do the travellers fall into?\nCustomer: We're mostly around 26-40 years old. But... speaking of getting sick, what about *during* the trip? My partner has high blood pressure. Do we need to declare high blood pressure? What if something happens over there? The medical bills... I can't even think about it. We absolutely need good medical coverage.\nCustomer Service Agent: Thank you for letting me know. Yes, it's important we note any pre-existing conditions like high blood pressure. So, comprehensive medical cover is a priority. Understood. While you're in Japan for the two weeks, are you planning on doing any specific activities, perhaps like winter sports or diving?\nCustomer: Oh gosh, yes! We were hoping to try some skiing. I hadn't even properly considered... what if one of us gets injured doing that? It's supposed to be fun but now I'm just picturing accidents. Yes, we need cover for that too, for sports and adventure activities, I suppose? This is so stressful.\nCustomer Service Agent: Okay, noted cover for specified sports like skiing. It's good you're thinking about these things now. How about your travel arrangements getting there and back? Are you concerned about potential issues with flights?\nCustomer: Oh don't even start! Flights are a nightmare sometimes. Last time we flew, there was a huge delay, we missed a connection... it was awful. Stuck in an airport, tired, hungry. If that happens again... the cost of hotels, food... Yes, we absolutely need cover for travel delays. Significant ones, I mean. The stress is just too much otherwise.\nCustomer Service Agent: Alright, cover for significant travel delays causing extra expenses like accommodation and meals. I understand. And related to travel, what about your belongings, your luggage?\nCustomer: My luggage! Oh my goodness, yes! Can you imagine getting there and your bags are just... gone? Or smashed up? All your clothes, everything... It would be a disaster. We'd have to buy everything. Yes, definitely need coverage for lost or damaged luggage. It's just one more thing to worry about.\nCustomer Service Agent: Okay, cover for lost, damaged, or delayed luggage. I've noted that down. Just one more area to consider. With everything going on in the world, do you have any concerns regarding the safety situation, even in a place like Japan? And also, just so we have an idea for finding suitable options later, do you have a rough budget in mind for the insurance policy itself?\nCustomer: Honestly? Yes. I know Japan is generally safe, but you see things on the news... unexpected events, political things... It just adds to the anxiety. It feels silly, maybe, but having some kind of cover for... I don't know, war and political unrest? Just in case? It would make me feel a bit less panicked. As for budget... We're hoping to spend around $400 for the insurance for both of us. Is that realistic with all this...? I feel like I'm asking for everything.\nCustomer Service Agent: Thank you for sharing that. It's always better to consider all possibilities. Okay, so let me quickly summarize the requirements you've mentioned just to make sure I have everything correct. You're looking for travel insurance for two travellers, aged 26-40, travelling to Japan for two weeks. One traveller has pre-existing high blood pressure. You require cover for: Trip Cancellation, comprehensive Medical Coverage, Sports and Adventure Activities like skiing, significant Travel Delays, Lost or Damaged Luggage, and also War and Political Unrest cover. And your budget is around $400. Is that all correct?\nCustomer: Yes... yes, that sounds right. Hearing it listed out like that... it's a lot, but yes, that's what we need to feel secure. Thank you for being so patient, I know I sound a bit frantic.\nCustomer Service Agent: Not at all, it's completely understandable. My job is just to gather these details accurately for you. Thank you for providing all the information. What will happen next is that we will use these requirements to identify suitable policy options, and a colleague from our sales team will be in touch shortly to discuss those specific plans and provide quotes.\nCustomer: Okay. Thank you, Sarah. I appreciate your help.\nCustomer Service Agent: You're most welcome. Thank you for calling ISS Insurance Ltd. Have a good day.\nCustomer: You too. Bye.\n",
            "name": null,
            "expected_output": "A JSON object that matches the TravelInsuranceRequirement model.",
            "summary": "Analyze the travel insurance call transcript below and extract key...",
            "raw": "{\n  \"requirement_id\": \"req_001\",\n  \"requirement_summary\": \"Travel insurance needed for a two-week trip to Japan for two travelers, including coverage for trip cancellation, medical expenses, skiing activities, travel delays, luggage, and political unrest.\",\n  \"detailed_description\": \"The customer is planning a trip to Japan for two weeks and requires travel insurance due to concerns about potential trip cancellations (e.g., sickness or family emergencies), medical coverage for one traveler with high blood pressure, coverage for skiing activities, coverage for significant travel delays, lost or damaged luggage, and insurance against war and political unrest. The travelers are aged 26-40, and they are budgeting around $400 for their insurance policy.\",\n  \"travel_destination\": \"Japan\",\n  \"travel_duration\": \"2 weeks\",\n  \"travel_start_date\": null,\n  \"travel_end_date\": null,\n  \"insurance_coverage_type\": [\n    \"Trip Cancellation\",\n    \"Medical Coverage\",\n    \"Sports and Adventure Activities\",\n    \"Travel Delays\",\n    \"Lost or Damaged Luggage\",\n    \"War and Political Unrest\"\n  ],\n  \"pre_existing_conditions\": [\n    \"High Blood Pressure\"\n  ],\n  \"age_group\": \"26-40\",\n  \"travelers_count\": 2,\n  \"traveler_details\": null,\n  \"budget_range\": \"$400\",\n  \"preferred_insurance_provider\": null,\n  \"additional_requests\": null,\n  \"keywords\": [\n    \"Travel Insurance\",\n    \"Japan\",\n    \"Trip Cancellation\",\n    \"Medical Coverage\",\n    \"Skiing\",\n    \"Travel Delays\",\n    \"Luggage\",\n    \"Political Unrest\"\n  ]\n}",
            "pydantic": null,
            "json_dict": {
                "requirement_id": "req_001",
                "requirement_summary": "Travel insurance needed for a two-week trip to Japan for two travelers, including coverage for trip cancellation, medical expenses, skiing activities, travel delays, luggage, and political unrest.",
                "detailed_description": "The customer is planning a trip to Japan for two weeks and requires travel insurance due to concerns about potential trip cancellations (e.g., sickness or family emergencies), medical coverage for one traveler with high blood pressure, coverage for skiing activities, coverage for significant travel delays, lost or damaged luggage, and insurance against war and political unrest. The travelers are aged 26-40, and they are budgeting around $400 for their insurance policy.",
                "travel_destination": "Japan",
                "travel_duration": "2 weeks",
                "travel_start_date": null,
                "travel_end_date": null,
                "insurance_coverage_type": [
                    "Trip Cancellation",
                    "Medical Coverage",
                    "Sports and Adventure Activities",
                    "Travel Delays",
                    "Lost or Damaged Luggage",
                    "War and Political Unrest"
                ],
                "pre_existing_conditions": [
                    "High Blood Pressure"
                ],
                "age_group": "26-40",
                "travelers_count": 2,
                "traveler_details": null,
                "budget_range": "$400",
                "preferred_insurance_provider": null,
                "additional_requests": null,
                "keywords": [
                    "Travel Insurance",
                    "Japan",
                    "Trip Cancellation",
                    "Medical Coverage",
                    "Skiing",
                    "Travel Delays",
                    "Luggage",
                    "Political Unrest"
                ]
            },
            "agent": "Call Transcript Analyst",
            "output_format": "json"
        }
    ],
    "token_usage": {
        "total_tokens": 4896,
        "prompt_tokens": 4082,
        "cached_prompt_tokens": 0,
        "completion_tokens": 814,
        "successful_requests": 2
    }
}