{
    "raw": "{\n  \"requirement_id\": \"REQ-0023\",\n  \"requirement_summary\": \"Travel insurance for two adults traveling from Singapore to Japan for two weeks.\",\n  \"detailed_description\": \"The customer requires a comprehensive travel insurance plan that addresses several key areas, including coverage for pre-existing medical conditions, specifically high blood pressure, and inquiries regarding trip cancellation, lost/damaged luggage, travel delays, and sports activities such as hiking. Additional inquiries include specific coverage details related to accidental death while using public transport and the budget for the insurance premium.\",\n  \"travel_origin\": \"Singapore\",\n  \"travel_destination\": \"Japan\",\n  \"travel_duration\": \"2 weeks\",\n  \"insurance_coverage_type\": [\n    \"Medical Coverage\",\n    \"Trip Cancellation\",\n    \"Lost/Damaged/Delayed Luggage\",\n    \"Travel Delays\",\n    \"Sports and Adventure Coverage\"\n  ],\n  \"pre_existing_conditions\": [\n    \"high blood pressure\"\n  ],\n  \"medical_needs\": [],\n  \"activities_to_cover\": [\n    \"hiking\"\n  ],\n  \"age_group\": \"41-55\",\n  \"additional_requests\": \"Details on the coverage limits and claim procedures for lost or damaged luggage; clarification on 'close family member' for trip cancellation; specifics on double indemnity for accidental death during public transport; confirmation on coverage exclusions for electronics and typical delay thresholds for reimbursements.\",\n  \"keywords\": [\n    \"travel insurance\",\n    \"Japan\",\n    \"hiking\",\n    \"high blood pressure\",\n    \"double indemnity\",\n    \"public transport\",\n    \"trip cancellation\",\n    \"travel delay\",\n    \"luggage coverage\",\n    \"premium budget\"\n  ]\n}",
    "pydantic": null,
    "json_dict": {
        "requirement_id": "REQ-0023",
        "requirement_summary": "Travel insurance for two adults traveling from Singapore to Japan for two weeks.",
        "detailed_description": "The customer requires a comprehensive travel insurance plan that addresses several key areas, including coverage for pre-existing medical conditions, specifically high blood pressure, and inquiries regarding trip cancellation, lost/damaged luggage, travel delays, and sports activities such as hiking. Additional inquiries include specific coverage details related to accidental death while using public transport and the budget for the insurance premium.",
        "travel_origin": "Singapore",
        "travel_destination": "Japan",
        "travel_duration": "2 weeks",
        "insurance_coverage_type": [
            "Medical Coverage",
            "Trip Cancellation",
            "Lost/Damaged/Delayed Luggage",
            "Travel Delays",
            "Sports and Adventure Coverage"
        ],
        "pre_existing_conditions": [
            "high blood pressure"
        ],
        "medical_needs": [],
        "activities_to_cover": [
            "hiking"
        ],
        "age_group": "41-55",
        "additional_requests": "Details on the coverage limits and claim procedures for lost or damaged luggage; clarification on 'close family member' for trip cancellation; specifics on double indemnity for accidental death during public transport; confirmation on coverage exclusions for electronics and typical delay thresholds for reimbursements.",
        "keywords": [
            "travel insurance",
            "Japan",
            "hiking",
            "high blood pressure",
            "double indemnity",
            "public transport",
            "trip cancellation",
            "travel delay",
            "luggage coverage",
            "premium budget"
        ]
    },
    "tasks_output": [
        {
            "description": "Analyze the travel insurance call transcript below and extract key customer requirements.\nStep 1: Read the transcript carefully and extract all relevant details. For each field in the schema, provide a brief annotation or reference to the specific portion(s) of the transcript where the detail was found.\nStep 2: Review your annotations to verify that every extracted detail directly matches the transcript. Resolve any discrepancies or conflicts in the data.\nStep 3: Produce a final, validated JSON object that adheres exactly to the TravelInsuranceRequirement schema\n\nIf a field is not mentioned in the transcript, use null.\n\nTranscript:\nCustomer Service Agent: Good morning, thank you for calling ISS Insurance Ltd. My name is Priya. How may I help you today?\nCustomer: Good morning, Priya. I'm calling to gather specific information required for obtaining a travel insurance quote. We'll be traveling from Singapore.\nCustomer Service Agent: Certainly, I can help you with that. Could you please provide some details about your trip? For instance, where will you be travelling to?\nCustomer: We're planning a trip to Japan.\nCustomer Service Agent: Japan, noted. And how long will your trip be?\nCustomer: It will be a 2 weeks trip.\nCustomer Service Agent: Alright, 2 weeks to Japan. And how many people will be travelling?\nCustomer: There will be 2 of us traveling.\nCustomer Service Agent: Okay, two travellers. Could you let me know the general age group of the travellers?\nCustomer: The travelers are in the 41-55 age group.\nCustomer Service Agent: Understood, 41-55. Are there any particular activities you have planned for this trip?\nCustomer: Yes, we plan to do some hiking during our trip. I need clarity on the coverage level for sports and adventure activities. Specifically, I'm interested in understanding the usual exclusions, like participation without proper guidance or activities against local advice.\nCustomer Service Agent: Okay, so you require information on the coverage specifics and exclusions related to hiking under the Sports and Adventure Activities benefit. Noted.\nCustomer: Correct. Also, regarding health matters, do we need to declare high blood pressure? One traveler has managed high blood pressure. I want to understand how this interacts with the emergency medical coverage and potential pre-existing condition clauses.\nCustomer Service Agent: Noted. You have a query regarding the declaration of high blood pressure and how it relates to the medical coverage, especially concerning pre-existing conditions. Are there any specific medical devices you need to bring, like a CPAP machine?\nCustomer: No, no special medical equipment needed.\nCustomer Service Agent: Okay. What other aspects of the coverage are important for you?\nCustomer: I've been reviewing general policy structures. I need details on the coverage limits and claim procedures for lost or damaged luggage. Specifically, what's the typical minimum delay duration before reimbursement for essential purchases is triggered under delayed baggage cover? Are items like cameras typically excluded from damage claims?\nCustomer Service Agent: Understood. You need details on lost, damaged, and delayed baggage coverage, including the delay threshold for essential purchases and typical exclusions like electronics.\nCustomer: Precisely. And concerning potential disruptions, I need to understand the travel delay benefit. What's the standard qualifying delay period, usually in hours, and what types of expenses, like accommodation or meals, are generally covered?\nCustomer Service Agent: Okay, details required on the travel delay benefit, specifically the minimum delay duration and covered expenses such as accommodation and meals.\nCustomer: Yes. Furthermore, regarding trip cancellation coverage. I understand standard covered reasons like unforeseen illness or natural disasters. I'd like clarification on how 'close family member' is typically defined in the context of cancellation due to bereavement.\nCustomer Service Agent: Noted. Clarification needed on the definition of 'close family member' within the trip cancellation benefit terms for bereavement.\nCustomer: And one final, very specific requirement. I want to know if the policy provides extra coverage if an accident happens while I'm on public transport. Does your policy offer a double payout for accidental death specifically if it occurs while traveling as a fare-paying passenger on scheduled public conveyance like a bus or train?\nCustomer Service Agent: Okay, I've noted that you require confirmation on whether the policy includes a specific benefit for double indemnity for accidental death occurring while travelling on public transport.\nCustomer: That covers the main points I needed to clarify for now. Our budget for the insurance premium is around $400 for the two of us.\nCustomer Service Agent: Thank you. So, just to summarise the requirements you've outlined: you're looking for travel insurance for two adults, aged 41-55, travelling from Singapore to Japan for two weeks. Key coverage areas you need information on are: Medical Coverage, specifically regarding pre-existing high blood pressure; Trip Cancellation, including the definition of 'close family member'; Lost/Damaged/Delayed Luggage, including delay thresholds and electronics exclusions; Travel Delays, specifically the qualifying duration and covered expenses; Sports and Adventure cover related to hiking, including typical exclusions; and a specific feature regarding a double accidental death payout if occurring on public transport. You also mentioned a premium budget of around $400. Is that all correct?\nCustomer: Yes, that accurately captures all my requirements.\nCustomer Service Agent: Excellent. Thank you for providing those details clearly. I have recorded all these requirements. The next step would be for our sales team to use this information to identify the most suitable policy options and provide you with specific quotes and policy wording details. Shall I arrange for them to contact you?\nCustomer: Yes, please do. Thank you for your efficient assistance, Priya.\nCustomer Service Agent: You're welcome. Thank you for calling ISS Insurance Ltd. Have a great day.\nCustomer: You too. Goodbye.\n",
            "name": null,
            "expected_output": "A JSON object that matches the TravelInsuranceRequirement model.",
            "summary": "Analyze the travel insurance call transcript below and extract key...",
            "raw": "{\n  \"requirement_id\": \"REQ-0023\",\n  \"requirement_summary\": \"Travel insurance for two adults traveling from Singapore to Japan for two weeks.\",\n  \"detailed_description\": \"The customer requires a comprehensive travel insurance plan that addresses several key areas, including coverage for pre-existing medical conditions, specifically high blood pressure, and inquiries regarding trip cancellation, lost/damaged luggage, travel delays, and sports activities such as hiking. Additional inquiries include specific coverage details related to accidental death while using public transport and the budget for the insurance premium.\",\n  \"travel_origin\": \"Singapore\",\n  \"travel_destination\": \"Japan\",\n  \"travel_duration\": \"2 weeks\",\n  \"insurance_coverage_type\": [\n    \"Medical Coverage\",\n    \"Trip Cancellation\",\n    \"Lost/Damaged/Delayed Luggage\",\n    \"Travel Delays\",\n    \"Sports and Adventure Coverage\"\n  ],\n  \"pre_existing_conditions\": [\n    \"high blood pressure\"\n  ],\n  \"medical_needs\": [],\n  \"activities_to_cover\": [\n    \"hiking\"\n  ],\n  \"age_group\": \"41-55\",\n  \"additional_requests\": \"Details on the coverage limits and claim procedures for lost or damaged luggage; clarification on 'close family member' for trip cancellation; specifics on double indemnity for accidental death during public transport; confirmation on coverage exclusions for electronics and typical delay thresholds for reimbursements.\",\n  \"keywords\": [\n    \"travel insurance\",\n    \"Japan\",\n    \"hiking\",\n    \"high blood pressure\",\n    \"double indemnity\",\n    \"public transport\",\n    \"trip cancellation\",\n    \"travel delay\",\n    \"luggage coverage\",\n    \"premium budget\"\n  ]\n}",
            "pydantic": null,
            "json_dict": {
                "requirement_id": "REQ-0023",
                "requirement_summary": "Travel insurance for two adults traveling from Singapore to Japan for two weeks.",
                "detailed_description": "The customer requires a comprehensive travel insurance plan that addresses several key areas, including coverage for pre-existing medical conditions, specifically high blood pressure, and inquiries regarding trip cancellation, lost/damaged luggage, travel delays, and sports activities such as hiking. Additional inquiries include specific coverage details related to accidental death while using public transport and the budget for the insurance premium.",
                "travel_origin": "Singapore",
                "travel_destination": "Japan",
                "travel_duration": "2 weeks",
                "insurance_coverage_type": [
                    "Medical Coverage",
                    "Trip Cancellation",
                    "Lost/Damaged/Delayed Luggage",
                    "Travel Delays",
                    "Sports and Adventure Coverage"
                ],
                "pre_existing_conditions": [
                    "high blood pressure"
                ],
                "medical_needs": [],
                "activities_to_cover": [
                    "hiking"
                ],
                "age_group": "41-55",
                "additional_requests": "Details on the coverage limits and claim procedures for lost or damaged luggage; clarification on 'close family member' for trip cancellation; specifics on double indemnity for accidental death during public transport; confirmation on coverage exclusions for electronics and typical delay thresholds for reimbursements.",
                "keywords": [
                    "travel insurance",
                    "Japan",
                    "hiking",
                    "high blood pressure",
                    "double indemnity",
                    "public transport",
                    "trip cancellation",
                    "travel delay",
                    "luggage coverage",
                    "premium budget"
                ]
            },
            "agent": "Call Transcript Analyst",
            "output_format": "json"
        }
    ],
    "token_usage": {
        "total_tokens": 48657,
        "prompt_tokens": 40570,
        "cached_prompt_tokens": 0,
        "completion_tokens": 8087,
        "successful_requests": 27
    }
}